Workbook

Sheet Lisez-moi
B2: Suivi des réindexations de loyers – SCI EXEMPLE (DÉMO)
B3: Généré le 09/09/2026 – indexation_loyer v0.1.0
B5: ⚠ CLASSEUR DE DÉMONSTRATION : tous les indices et tous les baux sont FICTIFS. Ne pas utiliser pour un calcul réel.
B7: Derniers indices connus dans ce classeur
B8: Série | C8: Dernier trimestre | D8: Valeur | E8: Statut | F8: MAJ INSEE | G8: Source
B9: ILC – Indice des loyers commerciaux (ILC) - Base 100 au 1er trimestre 2008 | C9: 2026-T1 | D9: 124.4 | E9: Provisoire | F9: 2026-09-09 | G9: FICTIF_DEMO
B10: ILAT – Indice des loyers des activités tertiaires (ILAT) - Base 100 au 1er trimestre 2010 | C10: 2026-T1 | D10: 121.2 | E10: Provisoire | F10: 2026-09-09 | G10: FICTIF_DEMO
B11: ICC – Indice du coût de la construction des immeubles à usage d'habitation (ICC) - Base 100 au 4e trimestre 1953 | C11: 2026-T1 | D11: 1892 | E11: Provisoire | F11: 2026-09-09 | G11: FICTIF_DEMO
B12: IRL – Indice de référence des loyers (IRL) - Base 100 au 4e trimestre 1998 | C12: 2026-T1 | D12: 137.6 | E12: Provisoire | F12: 2026-09-09 | G12: FICTIF_DEMO
B14: Mode d'emploi
B15: 1. Feuille « Baux » : une ligne par local / bail. Seules les cellules jaunes se saisissent. La colonne Contrôles signale les incohérences.
B16: 2. Feuille « Indices » : alimentée par la commande python -m indexation_loyer fetch-indices puis refresh <société>. Ne pas saisir ici sauf ligne de source MANUEL.
B17: 3. Feuille « Révisions » : calendrier calculé. Statut ✔ Calculable = l'indice est publié et la date de révision est passée : la facturation doit être ajustée.
B18: Colonne « Décision » : vide ou Appliquer = révision appliquée ; Geler = le client renonce à la révision (loyer inchangé). « Geler – rattrapage possible » permet de récupérer la variation à la révision suivante ; « sans rattrapage » l'abandonne.
B19: Colonne « Consigne (à faire) » : instruction libre du dossier (ex. « Gel décidé par le client le 12/03, courrier à envoyer, ne pas facturer »). Reprise dans la feuille Alertes.
B20: Renseigner « Appliqué ? », la date d'application et la date d'envoi du courrier : toutes les colonnes jaunes sont conservées au rafraîchissement.
B21: Courriers aux locataires : commande python -m indexation_loyer courriers <société> -> un PDF par échéance à notifier (application ou gel), modèle dans config/courrier_modele.json.
B22: 4. Feuille « Alertes » : vue de pilotage par bail (loyer actuel, prochaine échéance, action).
B23: 5. Feuille « Pennylane » : corps de requête prêt pour POST /billing_subscriptions (mode aperçu ; l'envoi se fait par la commande pennylane <société>).
B24: Trimestres : notation AAAA-Tn (2024-T2 = 2e trimestre 2024), équivalente au 2024-Q2 de l'INSEE.
B25: Convention par défaut du trimestre de base : dernier indice publié à la date de prise d'effet (T-2). À caler sur la clause du bail.
... B34: Légende : fond jaune = saisie ; autres cellules = formules ; ne pas insérer de colonnes dans Baux, Indices, Révisions.

Sheet Société
A1: Raison sociale | B1: SCI EXEMPLE (DÉMO)
A2: SIREN | B2: 000000000
A3: Forme | B3: SCI
A4: Régime TVA des loyers | B4: Loyers soumis à TVA sur option (20 %)
A5: Identifiant société Pennylane
A6: Contact cabinet | B6: cabinet – démonstration
A7: Adresse du bailleur (courriers) | B7: 1 place de la Bourse 75002 Paris
A8: Signataire des courriers | B8: Mme Claire Exemple
A9: Qualité du signataire | B9: Gérante
A10: Ville de signature | B10: Paris
A11: Date de génération | B11: 46274
A12: Mode démonstration | B12: OUI

Sheet Baux
A1: ID bail | B1: Local (désignation / adresse) | C1: Locataire | D1: Adresse du locataire (courrier) | E1: Type de bail | F1: Date de prise d'effet | G1: Durée (ans) | H1: Date de fin | I1: Loyer initial annuel HT | J1: Charges annuelles HT | K1: TVA (%) | L1: Périodicité de facturation | M1: Indice | N1: Trimestre indice de base | O1: Périodicité de révision (ans) | P1: Méthode | Q1: Plafond annuel (%) – optionnel | R1: Pennylane customer_id | S1: Pennylane product_id | T1: Notes | U1: Contrôles
A2: B01 | B2: Boutique 12 rue de la Paix | C2: Boulangerie Dupont SAS | D2: 12 rue de la Paix 75002 Paris | E2: Commercial | F2: 44287 | G2: 9 | H2: =IF(OR(F2="",G2=""),"",EDATE(F2,12*G2)) | I2: 24000 | J2: 2400 | K2: 20 | L2: Mensuelle | M2: ILC | N2: 2020-T4 | O2: 1 | P2: Chaînée | R2: 100001 | T2: Clause d'échelle mobile annuelle, ILC même trimestre | U2: =IF(A2="","",TRIM(IF(F2="","Date d'effet manquante. ","")&IF(NOT(ISNUMBER(I2)),"Loyer initial manquant. ","")&IF(COUNTIF(Indices!$A:$A,M2)=0,"Aucune valeur d'indice chargée pour cette série. ","")&IF(SUMIFS(Indices!$C:$C,Indices!$A:$A,M2,Indices!$B:$B,N2)=0,"Indice de base "&N2&" absent de la feuille Indices. ","")&IF(LEN(N2)<>7,"Trimestre de base au format AAAA-Tn. ","")&IF(COUNTIF($A$2:$A$200,A2)>1,"ID bail en doublon. ","")&IF(AND(Q2<>"",NOT(ISNUMBER(Q2))),"Plafond non numérique. ","")&IF(COUNTIF($A$2:$A$200,A2)=1,"",""))&IF(AND(F2<>"",ISNUMBER(I2),SUMIFS(Indices!$C:$C,Indices!$A:$A,M2,Indices!$B:$B,N2)>0,LEN(N2)=7,COUNTIF($A$2:$A$200,A2)=1),"OK",""))
A3: B02 | B3: Bureaux 2e étage – 8 av. Foch | C3: Cabinet Martin (SELARL) | E3: Commercial | F3: 44835 | G3: 9 | H3: =IF(OR(F3="",G3=""),"",EDATE(F3,12*G3)) | I3: 36000 | J3: 0 | K3: 20 | L3: Trimestrielle | M3: ILAT | N3: 2022-T2 | O3: 3 | P3: Base fixe | R3: 100002 | T3: Révision triennale indexée ILAT, indice de base fixe | U3: =IF(A3="","",TRIM(IF(F3="","Date d'effet manquante. ","")&IF(NOT(ISNUMBER(I3)),"Loyer initial manquant. ","")&IF(COUNTIF(Indices!$A:$A,M3)=0,"Aucune valeur d'indice chargée pour cette série. ","")&IF(SUMIFS(Indices!$C:$C,Indices!$A:$A,M3,Indices!$B:$B,N3)=0,"Indice de base "&N3&" absent de la feuille Indices. ","")&IF(LEN(N3)<>7,"Trimestre de base au format AAAA-Tn. ","")&IF(COUNTIF($A$2:$A$200,A3)>1,"ID bail en doublon. ","")&IF(AND(Q3<>"",NOT(ISNUMBER(Q3))),"Plafond non numérique. ","")&IF(COUNTIF($A$2:$A$200,A3)=1,"",""))&IF(AND(F3<>"",ISNUMBER(I3),SUMIFS(Indices!$C:$C,Indices!$A:$A,M3,Indices!$B:$B,N3)>0,LEN(N3)=7,COUNTIF($A$2:$A$200,A3)=1),"OK",""))
A4: B03 | B4: Entrepôt ZA des Landes | C4: Logistix SARL | E4: Commercial | F4: 43480 | G4: 9 | H4: =IF(OR(F4="",G4=""),"",EDATE(F4,12*G4)) | I4: 60000 | J4: 6000 | K4: 20 | L4: Trimestrielle | M4: ICC | N4: 2018-T3 | O4: 1 | P4: Chaînée | Q4: 3.5 | T4: Bail antérieur à 2014 renouvelé, clause ICC ; plafond contractuel 3,5 % | U4: =IF(A4="","",TRIM(IF(F4="","Date d'effet manquante. ","")&IF(NOT(ISNUMBER(I4)),"Loyer initial manquant. ","")&IF(COUNTIF(Indices!$A:$A,M4)=0,"Aucune valeur d'indice chargée pour cette série. ","")&IF(SUMIFS(Indices!$C:$C,Indices!$A:$A,M4,Indices!$B:$B,N4)=0,"Indice de base "&N4&" absent de la feuille Indices. ","")&IF(LEN(N4)<>7,"Trimestre de base au format AAAA-Tn. ","")&IF(COUNTIF($A$2:$A$200,A4)>1,"ID bail en doublon. ","")&IF(AND(Q4<>"",NOT(ISNUMBER(Q4))),"Plafond non numérique. ","")&IF(COUNTIF($A$2:$A$200,A4)=1,"",""))&IF(AND(F4<>"",ISNUMBER(I4),SUMIFS(Indices!$C:$C,Indices!$A:$A,M4,Indices!$B:$B,N4)>0,LEN(N4)=7,COUNTIF($A$2:$A$200,A4)=1),"OK",""))
A5: B04 | B5: Local 45 bd Haussmann | C5: Nouveau preneur (à compléter) | E5: Commercial | F5: 45839 | G5: 9 | H5: =IF(OR(F5="",G5=""),"",EDATE(F5,12*G5)) | I5: 18000 | J5: 0 | K5: 20 | L5: Mensuelle | M5: ILC | N5: 2025-T1 | O5: 1 | P5: Chaînée | T5: customer_id Pennylane à créer | U5: =IF(A5="","",TRIM(IF(F5="","Date d'effet manquante. ","")&IF(NOT(ISNUMBER(I5)),"Loyer initial manquant. ","")&IF(COUNTIF(Indices!$A:$A,M5)=0,"Aucune valeur d'indice chargée pour cette série. ","")&IF(SUMIFS(Indices!$C:$C,Indices!$A:$A,M5,Indices!$B:$B,N5)=0,"Indice de base "&N5&" absent de la feuille Indices. ","")&IF(LEN(N5)<>7,"Trimestre de base au format AAAA-Tn. ","")&IF(COUNTIF($A$2:$A$200,A5)>1,"ID bail en doublon. ","")&IF(AND(Q5<>"",NOT(ISNUMBER(Q5))),"Plafond non numérique. ","")&IF(COUNTIF($A$2:$A$200,A5)=1,"",""))&IF(AND(F5<>"",ISNUMBER(I5),SUMIFS(Indices!$C:$C,Indices!$A:$A,M5,Indices!$B:$B,N5)>0,LEN(N5)=7,COUNTIF($A$2:$A$200,A5)=1),"OK",""))

Sheet Indices
A1: Série | B1: Période | C1: Valeur | D1: Statut obs. | E1: Dernière MAJ INSEE | F1: Source | G1: Date extraction | H1: Variation annuelle
A2: ICC | B2: 2018-T1 | C2: 1700 | D2: A | E2: 2026-09-09 | F2: FICTIF_DEMO | G2: 2026-09-09 | H2: =IFERROR(C2/SUMIFS($C:$C,$A:$A,A2,$B:$B,TEXT(VALUE(LEFT(B2,4))-1,"0")&RIGHT(B2,3))-1,"")
A3: ICC | B3: 2018-T2 | C3: 1708 | D3: A | E3: 2026-09-09 | F3: FICTIF_DEMO | G3: 2026-09-09 | H3: =IFERROR(C3/SUMIFS($C:$C,$A:$A,A3,$B:$B,TEXT(VALUE(LEFT(B3,4))-1,"0")&RIGHT(B3,3))-1,"")
A4: ICC | B4: 2018-T3 | C4: 1716 | D4: A | E4: 2026-09-09 | F4: FICTIF_DEMO | G4: 2026-09-09 | H4: =IFERROR(C4/SUMIFS($C:$C,$A:$A,A4,$B:$B,TEXT(VALUE(LEFT(B4,4))-1,"0")&RIGHT(B4,3))-1,"")
A5: ICC | B5: 2018-T4 | C5: 1724 | D5: A | E5: 2026-09-09 | F5: FICTIF_DEMO | G5: 2026-09-09 | H5: =IFERROR(C5/SUMIFS($C:$C,$A:$A,A5,$B:$B,TEXT(VALUE(LEFT(B5,4))-1,"0")&RIGHT(B5,3))-1,"")
A6: ICC | B6: 2019-T1 | C6: 1732 | D6: A | E6: 2026-09-09 | F6: FICTIF_DEMO | G6: 2026-09-09 | H6: =IFERROR(C6/SUMIFS($C:$C,$A:$A,A6,$B:$B,TEXT(VALUE(LEFT(B6,4))-1,"0")&RIGHT(B6,3))-1,"")
A7: ICC | B7: 2019-T2 | C7: 1740 | D7: A | E7: 2026-09-09 | F7: FICTIF_DEMO | G7: 2026-09-09 | H7: =IFERROR(C7/SUMIFS($C:$C,$A:$A,A7,$B:$B,TEXT(VALUE(LEFT(B7,4))-1,"0")&RIGHT(B7,3))-1,"")
A8: ICC | B8: 2019-T3 | C8: 1748 | D8: A | E8: 2026-09-09 | F8: FICTIF_DEMO | G8: 2026-09-09 | H8: =IFERROR(C8/SUMIFS($C:$C,$A:$A,A8,$B:$B,TEXT(VALUE(LEFT(B8,4))-1,"0")&RIGHT(B8,3))-1,"")
A9: ICC | B9: 2019-T4 | C9: 1756 | D9: A | E9: 2026-09-09 | F9: FICTIF_DEMO | G9: 2026-09-09 | H9: =IFERROR(C9/SUMIFS($C:$C,$A:$A,A9,$B:$B,TEXT(VALUE(LEFT(B9,4))-1,"0")&RIGHT(B9,3))-1,"")
A10: ICC | B10: 2020-T1 | C10: 1764 | D10: A | E10: 2026-09-09 | F10: FICTIF_DEMO | G10: 2026-09-09 | H10: =IFERROR(C10/SUMIFS($C:$C,$A:$A,A10,$B:$B,TEXT(VALUE(LEFT(B10,4))-1,"0")&RIGHT(B10,3))-1,"")
A11: ICC | B11: 2020-T2 | C11: 1772 | D11: A | E11: 2026-09-09 | F11: FICTIF_DEMO | G11: 2026-09-09 | H11: =IFERROR(C11/SUMIFS($C:$C,$A:$A,A11,$B:$B,TEXT(VALUE(LEFT(B11,4))-1,"0")&RIGHT(B11,3))-1,"")
A12: ICC | B12: 2020-T3 | C12: 1780 | D12: A | E12: 2026-09-09 | F12: FICTIF_DEMO | G12: 2026-09-09 | H12: =IFERROR(C12/SUMIFS($C:$C,$A:$A,A12,$B:$B,TEXT(VALUE(LEFT(B12,4))-1,"0")&RIGHT(B12,3))-1,"")
A13: ICC | B13: 2020-T4 | C13: 1788 | D13: A | E13: 2026-09-09 | F13: FICTIF_DEMO | G13: 2026-09-09 | H13: =IFERROR(C13/SUMIFS($C:$C,$A:$A,A13,$B:$B,TEXT(VALUE(LEFT(B13,4))-1,"0")&RIGHT(B13,3))-1,"")
... A133: IRL | B133: 2026-T1 | C133: 137.6 | D133: P | E133: 2026-09-09 | F133: FICTIF_DEMO | G133: 2026-09-09 | H133: =IFERROR(C133/SUMIFS($C:$C,$A:$A,A133,$B:$B,TEXT(VALUE(LEFT(B133,4))-1,"0")&RIGHT(B133,3))-1,"")

Sheet Révisions
A1: ID bail | B1: Local | C1: N° | D1: Date de révision | E1: Indice | F1: Trim. référence | G1: Valeur indice réf. | H1: Trim. précédent | I1: Valeur indice préc. | J1: Coefficient | K1: Décision | L1: Base de calcul (annuel HT) | M1: Loyer révisé brut | N1: Loyer retenu (annuel HT) | O1: Loyer précédent (annuel HT) | P1: Variation | Q1: Loyer mensuel HT | R1: Loyer / échéance HT | S1: Charges / échéance HT | T1: TVA / échéance | U1: Total TTC / échéance | V1: Statut | W1: Consigne (à faire) | X1: Appliqué ? (Oui/Non) | Y1: Date d'application | Z1: Courrier envoyé le | AA1: Commentaire | AB1: Clé | AC1: Effectif
A2: B01 | B2: =INDEX(Baux!$B:$B,MATCH($A2,Baux!$A:$A,0)) | C2: 1 | D2: =EDATE(INDEX(Baux!$F:$F,MATCH($A2,Baux!$A:$A,0)),12*INDEX(Baux!$O:$O,MATCH($A2,Baux!$A:$A,0))*C2) | E2: =INDEX(Baux!$M:$M,MATCH($A2,Baux!$A:$A,0)) | F2: =TEXT(VALUE(LEFT(INDEX(Baux!$N:$N,MATCH($A2,Baux!$A:$A,0)),4))+C2*INDEX(Baux!$O:$O,MATCH($A2,Baux!$A:$A,0)),"0")&RIGHT(INDEX(Baux!$N:$N,MATCH($A2,Baux!$A:$A,0)),3) | G2: =IF(SUMIFS(Indices!$C:$C,Indices!$A:$A,E2,Indices!$B:$B,F2)=0,"",SUMIFS(Indices!$C:$C,Indices!$A:$A,E2,Indices!$B:$B,F2)) | H2: =INDEX(Baux!$N:$N,MATCH($A2,Baux!$A:$A,0)) | I2: =IF(SUMIFS(Indices!$C:$C,Indices!$A:$A,E2,Indices!$B:$B,H2)=0,"",SUMIFS(Indices!$C:$C,Indices!$A:$A,E2,Indices!$B:$B,H2)) | J2: =IF(OR(G2="",I2=""),"",G2/I2) | L2: =INDEX(Baux!$I:$I,MATCH($A2,Baux!$A:$A,0)) | M2: =IF(OR(J2="",L2=""),"",ROUND(L2*J2,2)) | N2: =IF(LEFT(K2,5)="Geler",O2,IF(M2="","",IF(INDEX(Baux!$Q:$Q,MATCH($A2,Baux!$A:$A,0))="",M2,MIN(M2,ROUND(L2*(1+INDEX(Baux!$Q:$Q,MATCH($A2,Baux!$A:$A,0))/100)^IF(INDEX(Baux!$P:$P,MATCH($A2,Baux!$A:$A,0))="Base fixe",C2*INDEX(Baux!$O:$O,MATCH($A2,Baux!$A:$A,0)),VALUE(LEFT(F2,4))-VALUE(LEFT(H2,4))),2))))) | O2: =INDEX(Baux!$I:$I,MATCH($A2,Baux!$A:$A,0)) | P2: =IF(OR(N2="",O2=""),"",N2/O2-1) | Q2: =IF(N2="","",N2/12) | R2: =IF(N2="","",N2/IF(INDEX(Baux!$L:$L,MATCH($A2,Baux!$A:$A,0))="Mensuelle",12,IF(INDEX(Baux!$L:$L,MATCH($A2,Baux!$A:$A,0))="Trimestrielle",4,IF(INDEX(Baux!$L:$L,MATCH($A2,Baux!$A:$A,0))="Semestrielle",2,1)))) | S2: =IF(INDEX(Baux!$J:$J,MATCH($A2,Baux!$A:$A,0))="",0,INDEX(Baux!$J:$J,MATCH($A2,Baux!$A:$A,0)))/IF(INDEX(Baux!$L:$L,MATCH($A2,Baux!$A:$A,0))="Mensuelle",12,IF(INDEX(Baux!$L:$L,MATCH($A2,Baux!$A:$A,0))="Trimestrielle",4,IF(INDEX(Baux!$L:$L,MATCH($A2,Baux!$A:$A,0))="Semestrielle",2,1))) | T2: =IF(R2="","",(R2+S2)*INDEX(Baux!$K:$K,MATCH($A2,Baux!$A:$A,0))/100) | U2: =IF(R2="","",R2+S2+T2) | V2: =IF(LEFT(K2,5)="Geler","❄ Gelée",IF(G2="",IF(D2<=TODAY(),"⚠ Indice attendu","À venir"),IF(D2<=TODAY(),"✔ Calculable","Indice connu – à venir"))) | X2: Oui | AB2: =A2&"#"&C2 | AC2: =IF(AND(D2<=TODAY(),N2<>""),1,0)
A3: B01 | B3: =INDEX(Baux!$B:$B,MATCH($A3,Baux!$A:$A,0)) | C3: 2 | D3: =EDATE(INDEX(Baux!$F:$F,MATCH($A3,Baux!$A:$A,0)),12*INDEX(Baux!$O:$O,MATCH($A3,Baux!$A:$A,0))*C3) | E3: =INDEX(Baux!$M:$M,MATCH($A3,Baux!$A:$A,0)) | F3: =TEXT(VALUE(LEFT(INDEX(Baux!$N:$N,MATCH($A3,Baux!$A:$A,0)),4))+C3*INDEX(Baux!$O:$O,MATCH($A3,Baux!$A:$A,0)),"0")&RIGHT(INDEX(Baux!$N:$N,MATCH($A3,Baux!$A:$A,0)),3) | G3: =IF(SUMIFS(Indices!$C:$C,Indices!$A:$A,E3,Indices!$B:$B,F3)=0,"",SUMIFS(Indices!$C:$C,Indices!$A:$A,E3,Indices!$B:$B,F3)) | H3: =IF(INDEX(Baux!$P:$P,MATCH($A3,Baux!$A:$A,0))="Base fixe",INDEX(Baux!$N:$N,MATCH($A3,Baux!$A:$A,0)),IF(K2="Geler – rattrapage possible",H2,F2)) | I3: =IF(SUMIFS(Indices!$C:$C,Indices!$A:$A,E3,Indices!$B:$B,H3)=0,"",SUMIFS(Indices!$C:$C,Indices!$A:$A,E3,Indices!$B:$B,H3)) | J3: =IF(OR(G3="",I3=""),"",G3/I3) | L3: =IF(INDEX(Baux!$P:$P,MATCH($A3,Baux!$A:$A,0))="Base fixe",INDEX(Baux!$I:$I,MATCH($A3,Baux!$A:$A,0)),N2) | M3: =IF(OR(J3="",L3=""),"",ROUND(L3*J3,2)) | N3: =IF(LEFT(K3,5)="Geler",O3,IF(M3="","",IF(INDEX(Baux!$Q:$Q,MATCH($A3,Baux!$A:$A,0))="",M3,MIN(M3,ROUND(L3*(1+INDEX(Baux!$Q:$Q,MATCH($A3,Baux!$A:$A,0))/100)^IF(INDEX(Baux!$P:$P,MATCH($A3,Baux!$A:$A,0))="Base fixe",C3*INDEX(Baux!$O:$O,MATCH($A3,Baux!$A:$A,0)),VALUE(LEFT(F3,4))-VALUE(LEFT(H3,4))),2))))) | O3: =N2 | P3: =IF(OR(N3="",O3=""),"",N3/O3-1) | Q3: =IF(N3="","",N3/12) | R3: =IF(N3="","",N3/IF(INDEX(Baux!$L:$L,MATCH($A3,Baux!$A:$A,0))="Mensuelle",12,IF(INDEX(Baux!$L:$L,MATCH($A3,Baux!$A:$A,0))="Trimestrielle",4,IF(INDEX(Baux!$L:$L,MATCH($A3,Baux!$A:$A,0))="Semestrielle",2,1)))) | S3: =IF(INDEX(Baux!$J:$J,MATCH($A3,Baux!$A:$A,0))="",0,INDEX(Baux!$J:$J,MATCH($A3,Baux!$A:$A,0)))/IF(INDEX(Baux!$L:$L,MATCH($A3,Baux!$A:$A,0))="Mensuelle",12,IF(INDEX(Baux!$L:$L,MATCH($A3,Baux!$A:$A,0))="Trimestrielle",4,IF(INDEX(Baux!$L:$L,MATCH($A3,Baux!$A:$A,0))="Semestrielle",2,1))) | T3: =IF(R3="","",(R3+S3)*INDEX(Baux!$K:$K,MATCH($A3,Baux!$A:$A,0))/100) | U3: =IF(R3="","",R3+S3+T3) | V3: =IF(LEFT(K3,5)="Geler","❄ Gelée",IF(G3="",IF(D3<=TODAY(),"⚠ Indice attendu","À venir"),IF(D3<=TODAY(),"✔ Calculable","Indice connu – à venir"))) | X3: Oui | AB3: =A3&"#"&C3 | AC3: =IF(AND(D3<=TODAY(),N3<>""),1,0)
A4: B01 | B4: =INDEX(Baux!$B:$B,MATCH($A4,Baux!$A:$A,0)) | C4: 3 | D4: =EDATE(INDEX(Baux!$F:$F,MATCH($A4,Baux!$A:$A,0)),12*INDEX(Baux!$O:$O,MATCH($A4,Baux!$A:$A,0))*C4) | E4: =INDEX(Baux!$M:$M,MATCH($A4,Baux!$A:$A,0)) | F4: =TEXT(VALUE(LEFT(INDEX(Baux!$N:$N,MATCH($A4,Baux!$A:$A,0)),4))+C4*INDEX(Baux!$O:$O,MATCH($A4,Baux!$A:$A,0)),"0")&RIGHT(INDEX(Baux!$N:$N,MATCH($A4,Baux!$A:$A,0)),3) | G4: =IF(SUMIFS(Indices!$C:$C,Indices!$A:$A,E4,Indices!$B:$B,F4)=0,"",SUMIFS(Indices!$C:$C,Indices!$A:$A,E4,Indices!$B:$B,F4)) | H4: =IF(INDEX(Baux!$P:$P,MATCH($A4,Baux!$A:$A,0))="Base fixe",INDEX(Baux!$N:$N,MATCH($A4,Baux!$A:$A,0)),IF(K3="Geler – rattrapage possible",H3,F3)) | I4: =IF(SUMIFS(Indices!$C:$C,Indices!$A:$A,E4,Indices!$B:$B,H4)=0,"",SUMIFS(Indices!$C:$C,Indices!$A:$A,E4,Indices!$B:$B,H4)) | J4: =IF(OR(G4="",I4=""),"",G4/I4) | L4: =IF(INDEX(Baux!$P:$P,MATCH($A4,Baux!$A:$A,0))="Base fixe",INDEX(Baux!$I:$I,MATCH($A4,Baux!$A:$A,0)),N3) | M4: =IF(OR(J4="",L4=""),"",ROUND(L4*J4,2)) | N4: =IF(LEFT(K4,5)="Geler",O4,IF(M4="","",IF(INDEX(Baux!$Q:$Q,MATCH($A4,Baux!$A:$A,0))="",M4,MIN(M4,ROUND(L4*(1+INDEX(Baux!$Q:$Q,MATCH($A4,Baux!$A:$A,0))/100)^IF(INDEX(Baux!$P:$P,MATCH($A4,Baux!$A:$A,0))="Base fixe",C4*INDEX(Baux!$O:$O,MATCH($A4,Baux!$A:$A,0)),VALUE(LEFT(F4,4))-VALUE(LEFT(H4,4))),2))))) | O4: =N3 | P4: =IF(OR(N4="",O4=""),"",N4/O4-1) | Q4: =IF(N4="","",N4/12) | R4: =IF(N4="","",N4/IF(INDEX(Baux!$L:$L,MATCH($A4,Baux!$A:$A,0))="Mensuelle",12,IF(INDEX(Baux!$L:$L,MATCH($A4,Baux!$A:$A,0))="Trimestrielle",4,IF(INDEX(Baux!$L:$L,MATCH($A4,Baux!$A:$A,0))="Semestrielle",2,1)))) | S4: =IF(INDEX(Baux!$J:$J,MATCH($A4,Baux!$A:$A,0))="",0,INDEX(Baux!$J:$J,MATCH($A4,Baux!$A:$A,0)))/IF(INDEX(Baux!$L:$L,MATCH($A4,Baux!$A:$A,0))="Mensuelle",12,IF(INDEX(Baux!$L:$L,MATCH($A4,Baux!$A:$A,0))="Trimestrielle",4,IF(INDEX(Baux!$L:$L,MATCH($A4,Baux!$A:$A,0))="Semestrielle",2,1))) | T4: =IF(R4="","",(R4+S4)*INDEX(Baux!$K:$K,MATCH($A4,Baux!$A:$A,0))/100) | U4: =IF(R4="","",R4+S4+T4) | V4: =IF(LEFT(K4,5)="Geler","❄ Gelée",IF(G4="",IF(D4<=TODAY(),"⚠ Indice attendu","À venir"),IF(D4<=TODAY(),"✔ Calculable","Indice connu – à venir"))) | X4: Oui | Y4: 45383 | AB4: =A4&"#"&C4 | AC4: =IF(AND(D4<=TODAY(),N4<>""),1,0)
A5: B01 | B5: =INDEX(Baux!$B:$B,MATCH($A5,Baux!$A:$A,0)) | C5: 4 | D5: =EDATE(INDEX(Baux!$F:$F,MATCH($A5,Baux!$A:$A,0)),12*INDEX(Baux!$O:$O,MATCH($A5,Baux!$A:$A,0))*C5) | E5: =INDEX(Baux!$M:$M,MATCH($A5,Baux!$A:$A,0)) | F5: =TEXT(VALUE(LEFT(INDEX(Baux!$N:$N,MATCH($A5,Baux!$A:$A,0)),4))+C5*INDEX(Baux!$O:$O,MATCH($A5,Baux!$A:$A,0)),"0")&RIGHT(INDEX(Baux!$N:$N,MATCH($A5,Baux!$A:$A,0)),3) | G5: =IF(SUMIFS(Indices!$C:$C,Indices!$A:$A,E5,Indices!$B:$B,F5)=0,"",SUMIFS(Indices!$C:$C,Indices!$A:$A,E5,Indices!$B:$B,F5)) | H5: =IF(INDEX(Baux!$P:$P,MATCH($A5,Baux!$A:$A,0))="Base fixe",INDEX(Baux!$N:$N,MATCH($A5,Baux!$A:$A,0)),IF(K4="Geler – rattrapage possible",H4,F4)) | I5: =IF(SUMIFS(Indices!$C:$C,Indices!$A:$A,E5,Indices!$B:$B,H5)=0,"",SUMIFS(Indices!$C:$C,Indices!$A:$A,E5,Indices!$B:$B,H5)) | J5: =IF(OR(G5="",I5=""),"",G5/I5) | K5: Geler – sans rattrapage | L5: =IF(INDEX(Baux!$P:$P,MATCH($A5,Baux!$A:$A,0))="Base fixe",INDEX(Baux!$I:$I,MATCH($A5,Baux!$A:$A,0)),N4) | M5: =IF(OR(J5="",L5=""),"",ROUND(L5*J5,2)) | N5: =IF(LEFT(K5,5)="Geler",O5,IF(M5="","",IF(INDEX(Baux!$Q:$Q,MATCH($A5,Baux!$A:$A,0))="",M5,MIN(M5,ROUND(L5*(1+INDEX(Baux!$Q:$Q,MATCH($A5,Baux!$A:$A,0))/100)^IF(INDEX(Baux!$P:$P,MATCH($A5,Baux!$A:$A,0))="Base fixe",C5*INDEX(Baux!$O:$O,MATCH($A5,Baux!$A:$A,0)),VALUE(LEFT(F5,4))-VALUE(LEFT(H5,4))),2))))) | O5: =N4 | P5: =IF(OR(N5="",O5=""),"",N5/O5-1) | Q5: =IF(N5="","",N5/12) | R5: =IF(N5="","",N5/IF(INDEX(Baux!$L:$L,MATCH($A5,Baux!$A:$A,0))="Mensuelle",12,IF(INDEX(Baux!$L:$L,MATCH($A5,Baux!$A:$A,0))="Trimestrielle",4,IF(INDEX(Baux!$L:$L,MATCH($A5,Baux!$A:$A,0))="Semestrielle",2,1)))) | S5: =IF(INDEX(Baux!$J:$J,MATCH($A5,Baux!$A:$A,0))="",0,INDEX(Baux!$J:$J,MATCH($A5,Baux!$A:$A,0)))/IF(INDEX(Baux!$L:$L,MATCH($A5,Baux!$A:$A,0))="Mensuelle",12,IF(INDEX(Baux!$L:$L,MATCH($A5,Baux!$A:$A,0))="Trimestrielle",4,IF(INDEX(Baux!$L:$L,MATCH($A5,Baux!$A:$A,0))="Semestrielle",2,1))) | T5: =IF(R5="","",(R5+S5)*INDEX(Baux!$K:$K,MATCH($A5,Baux!$A:$A,0))/100) | U5: =IF(R5="","",R5+S5+T5) | V5: =IF(LEFT(K5,5)="Geler","❄ Gelée",IF(G5="",IF(D5<=TODAY(),"⚠ Indice attendu","À venir"),IF(D5<=TODAY(),"✔ Calculable","Indice connu – à venir"))) | W5: Gel décidé par la gérance le 12/03/2025 (difficultés du preneur). Ne pas facturer la hausse. Courrier d'information envoyé. | Z5: 45736 | AB5: =A5&"#"&C5 | AC5: =IF(AND(D5<=TODAY(),N5<>""),1,0)
A6: B01 | B6: =INDEX(Baux!$B:$B,MATCH($A6,Baux!$A:$A,0)) | C6: 5 | D6: =EDATE(INDEX(Baux!$F:$F,MATCH($A6,Baux!$A:$A,0)),12*INDEX(Baux!$O:$O,MATCH($A6,Baux!$A:$A,0))*C6) | E6: =INDEX(Baux!$M:$M,MATCH($A6,Baux!$A:$A,0)) | F6: =TEXT(VALUE(LEFT(INDEX(Baux!$N:$N,MATCH($A6,Baux!$A:$A,0)),4))+C6*INDEX(Baux!$O:$O,MATCH($A6,Baux!$A:$A,0)),"0")&RIGHT(INDEX(Baux!$N:$N,MATCH($A6,Baux!$A:$A,0)),3) | G6: =IF(SUMIFS(Indices!$C:$C,Indices!$A:$A,E6,Indices!$B:$B,F6)=0,"",SUMIFS(Indices!$C:$C,Indices!$A:$A,E6,Indices!$B:$B,F6)) | H6: =IF(INDEX(Baux!$P:$P,MATCH($A6,Baux!$A:$A,0))="Base fixe",INDEX(Baux!$N:$N,MATCH($A6,Baux!$A:$A,0)),IF(K5="Geler – rattrapage possible",H5,F5)) | I6: =IF(SUMIFS(Indices!$C:$C,Indices!$A:$A,E6,Indices!$B:$B,H6)=0,"",SUMIFS(Indices!$C:$C,Indices!$A:$A,E6,Indices!$B:$B,H6)) | J6: =IF(OR(G6="",I6=""),"",G6/I6) | L6: =IF(INDEX(Baux!$P:$P,MATCH($A6,Baux!$A:$A,0))="Base fixe",INDEX(Baux!$I:$I,MATCH($A6,Baux!$A:$A,0)),N5) | M6: =IF(OR(J6="",L6=""),"",ROUND(L6*J6,2)) | N6: =IF(LEFT(K6,5)="Geler",O6,IF(M6="","",IF(INDEX(Baux!$Q:$Q,MATCH($A6,Baux!$A:$A,0))="",M6,MIN(M6,ROUND(L6*(1+INDEX(Baux!$Q:$Q,MATCH($A6,Baux!$A:$A,0))/100)^IF(INDEX(Baux!$P:$P,MATCH($A6,Baux!$A:$A,0))="Base fixe",C6*INDEX(Baux!$O:$O,MATCH($A6,Baux!$A:$A,0)),VALUE(LEFT(F6,4))-VALUE(LEFT(H6,4))),2))))) | O6: =N5 | P6: =IF(OR(N6="",O6=""),"",N6/O6-1) | Q6: =IF(N6="","",N6/12) | R6: =IF(N6="","",N6/IF(INDEX(Baux!$L:$L,MATCH($A6,Baux!$A:$A,0))="Mensuelle",12,IF(INDEX(Baux!$L:$L,MATCH($A6,Baux!$A:$A,0))="Trimestrielle",4,IF(INDEX(Baux!$L:$L,MATCH($A6,Baux!$A:$A,0))="Semestrielle",2,1)))) | S6: =IF(INDEX(Baux!$J:$J,MATCH($A6,Baux!$A:$A,0))="",0,INDEX(Baux!$J:$J,MATCH($A6,Baux!$A:$A,0)))/IF(INDEX(Baux!$L:$L,MATCH($A6,Baux!$A:$A,0))="Mensuelle",12,IF(INDEX(Baux!$L:$L,MATCH($A6,Baux!$A:$A,0))="Trimestrielle",4,IF(INDEX(Baux!$L:$L,MATCH($A6,Baux!$A:$A,0))="Semestrielle",2,1))) | T6: =IF(R6="","",(R6+S6)*INDEX(Baux!$K:$K,MATCH($A6,Baux!$A:$A,0))/100) | U6: =IF(R6="","",R6+S6+T6) | V6: =IF(LEFT(K6,5)="Geler","❄ Gelée",IF(G6="",IF(D6<=TODAY(),"⚠ Indice attendu","À venir"),IF(D6<=TODAY(),"✔ Calculable","Indice connu – à venir"))) | AB6: =A6&"#"&C6 | AC6: =IF(AND(D6<=TODAY(),N6<>""),1,0)
A7: B01 | B7: =INDEX(Baux!$B:$B,MATCH($A7,Baux!$A:$A,0)) | C7: 6 | D7: =EDATE(INDEX(Baux!$F:$F,MATCH($A7,Baux!$A:$A,0)),12*INDEX(Baux!$O:$O,MATCH($A7,Baux!$A:$A,0))*C7) | E7: =INDEX(Baux!$M:$M,MATCH($A7,Baux!$A:$A,0)) | F7: =TEXT(VALUE(LEFT(INDEX(Baux!$N:$N,MATCH($A7,Baux!$A:$A,0)),4))+C7*INDEX(Baux!$O:$O,MATCH($A7,Baux!$A:$A,0)),"0")&RIGHT(INDEX(Baux!$N:$N,MATCH($A7,Baux!$A:$A,0)),3) | G7: =IF(SUMIFS(Indices!$C:$C,Indices!$A:$A,E7,Indices!$B:$B,F7)=0,"",SUMIFS(Indices!$C:$C,Indices!$A:$A,E7,Indices!$B:$B,F7)) | H7: =IF(INDEX(Baux!$P:$P,MATCH($A7,Baux!$A:$A,0))="Base fixe",INDEX(Baux!$N:$N,MATCH($A7,Baux!$A:$A,0)),IF(K6="Geler – rattrapage possible",H6,F6)) | I7: =IF(SUMIFS(Indices!$C:$C,Indices!$A:$A,E7,Indices!$B:$B,H7)=0,"",SUMIFS(Indices!$C:$C,Indices!$A:$A,E7,Indices!$B:$B,H7)) | J7: =IF(OR(G7="",I7=""),"",G7/I7) | L7: =IF(INDEX(Baux!$P:$P,MATCH($A7,Baux!$A:$A,0))="Base fixe",INDEX(Baux!$I:$I,MATCH($A7,Baux!$A:$A,0)),N6) | M7: =IF(OR(J7="",L7=""),"",ROUND(L7*J7,2)) | N7: =IF(LEFT(K7,5)="Geler",O7,IF(M7="","",IF(INDEX(Baux!$Q:$Q,MATCH($A7,Baux!$A:$A,0))="",M7,MIN(M7,ROUND(L7*(1+INDEX(Baux!$Q:$Q,MATCH($A7,Baux!$A:$A,0))/100)^IF(INDEX(Baux!$P:$P,MATCH($A7,Baux!$A:$A,0))="Base fixe",C7*INDEX(Baux!$O:$O,MATCH($A7,Baux!$A:$A,0)),VALUE(LEFT(F7,4))-VALUE(LEFT(H7,4))),2))))) | O7: =N6 | P7: =IF(OR(N7="",O7=""),"",N7/O7-1) | Q7: =IF(N7="","",N7/12) | R7: =IF(N7="","",N7/IF(INDEX(Baux!$L:$L,MATCH($A7,Baux!$A:$A,0))="Mensuelle",12,IF(INDEX(Baux!$L:$L,MATCH($A7,Baux!$A:$A,0))="Trimestrielle",4,IF(INDEX(Baux!$L:$L,MATCH($A7,Baux!$A:$A,0))="Semestrielle",2,1)))) | S7: =IF(INDEX(Baux!$J:$J,MATCH($A7,Baux!$A:$A,0))="",0,INDEX(Baux!$J:$J,MATCH($A7,Baux!$A:$A,0)))/IF(INDEX(Baux!$L:$L,MATCH($A7,Baux!$A:$A,0))="Mensuelle",12,IF(INDEX(Baux!$L:$L,MATCH($A7,Baux!$A:$A,0))="Trimestrielle",4,IF(INDEX(Baux!$L:$L,MATCH($A7,Baux!$A:$A,0))="Semestrielle",2,1))) | T7: =IF(R7="","",(R7+S7)*INDEX(Baux!$K:$K,MATCH($A7,Baux!$A:$A,0))/100) | U7: =IF(R7="","",R7+S7+T7) | V7: =IF(LEFT(K7,5)="Geler","❄ Gelée",IF(G7="",IF(D7<=TODAY(),"⚠ Indice attendu","À venir"),IF(D7<=TODAY(),"✔ Calculable","Indice connu – à venir"))) | AB7: =A7&"#"&C7 | AC7: =IF(AND(D7<=TODAY(),N7<>""),1,0)
A8: B01 | B8: =INDEX(Baux!$B:$B,MATCH($A8,Baux!$A:$A,0)) | C8: 7 | D8: =EDATE(INDEX(Baux!$F:$F,MATCH($A8,Baux!$A:$A,0)),12*INDEX(Baux!$O:$O,MATCH($A8,Baux!$A:$A,0))*C8) | E8: =INDEX(Baux!$M:$M,MATCH($A8,Baux!$A:$A,0)) | F8: =TEXT(VALUE(LEFT(INDEX(Baux!$N:$N,MATCH($A8,Baux!$A:$A,0)),4))+C8*INDEX(Baux!$O:$O,MATCH($A8,Baux!$A:$A,0)),"0")&RIGHT(INDEX(Baux!$N:$N,MATCH($A8,Baux!$A:$A,0)),3) | G8: =IF(SUMIFS(Indices!$C:$C,Indices!$A:$A,E8,Indices!$B:$B,F8)=0,"",SUMIFS(Indices!$C:$C,Indices!$A:$A,E8,Indices!$B:$B,F8)) | H8: =IF(INDEX(Baux!$P:$P,MATCH($A8,Baux!$A:$A,0))="Base fixe",INDEX(Baux!$N:$N,MATCH($A8,Baux!$A:$A,0)),IF(K7="Geler – rattrapage possible",H7,F7)) | I8: =IF(SUMIFS(Indices!$C:$C,Indices!$A:$A,E8,Indices!$B:$B,H8)=0,"",SUMIFS(Indices!$C:$C,Indices!$A:$A,E8,Indices!$B:$B,H8)) | J8: =IF(OR(G8="",I8=""),"",G8/I8) | L8: =IF(INDEX(Baux!$P:$P,MATCH($A8,Baux!$A:$A,0))="Base fixe",INDEX(Baux!$I:$I,MATCH($A8,Baux!$A:$A,0)),N7) | M8: =IF(OR(J8="",L8=""),"",ROUND(L8*J8,2)) | N8: =IF(LEFT(K8,5)="Geler",O8,IF(M8="","",IF(INDEX(Baux!$Q:$Q,MATCH($A8,Baux!$A:$A,0))="",M8,MIN(M8,ROUND(L8*(1+INDEX(Baux!$Q:$Q,MATCH($A8,Baux!$A:$A,0))/100)^IF(INDEX(Baux!$P:$P,MATCH($A8,Baux!$A:$A,0))="Base fixe",C8*INDEX(Baux!$O:$O,MATCH($A8,Baux!$A:$A,0)),VALUE(LEFT(F8,4))-VALUE(LEFT(H8,4))),2))))) | O8: =N7 | P8: =IF(OR(N8="",O8=""),"",N8/O8-1) | Q8: =IF(N8="","",N8/12) | R8: =IF(N8="","",N8/IF(INDEX(Baux!$L:$L,MATCH($A8,Baux!$A:$A,0))="Mensuelle",12,IF(INDEX(Baux!$L:$L,MATCH($A8,Baux!$A:$A,0))="Trimestrielle",4,IF(INDEX(Baux!$L:$L,MATCH($A8,Baux!$A:$A,0))="Semestrielle",2,1)))) | S8: =IF(INDEX(Baux!$J:$J,MATCH($A8,Baux!$A:$A,0))="",0,INDEX(Baux!$J:$J,MATCH($A8,Baux!$A:$A,0)))/IF(INDEX(Baux!$L:$L,MATCH($A8,Baux!$A:$A,0))="Mensuelle",12,IF(INDEX(Baux!$L:$L,MATCH($A8,Baux!$A:$A,0))="Trimestrielle",4,IF(INDEX(Baux!$L:$L,MATCH($A8,Baux!$A:$A,0))="Semestrielle",2,1))) | T8: =IF(R8="","",(R8+S8)*INDEX(Baux!$K:$K,MATCH($A8,Baux!$A:$A,0))/100) | U8: =IF(R8="","",R8+S8+T8) | V8: =IF(LEFT(K8,5)="Geler","❄ Gelée",IF(G8="",IF(D8<=TODAY(),"⚠ Indice attendu","À venir"),IF(D8<=TODAY(),"✔ Calculable","Indice connu – à venir"))) | AB8: =A8&"#"&C8 | AC8: =IF(AND(D8<=TODAY(),N8<>""),1,0)
A9: B01 | B9: =INDEX(Baux!$B:$B,MATCH($A9,Baux!$A:$A,0)) | C9: 8 | D9: =EDATE(INDEX(Baux!$F:$F,MATCH($A9,Baux!$A:$A,0)),12*INDEX(Baux!$O:$O,MATCH($A9,Baux!$A:$A,0))*C9) | E9: =INDEX(Baux!$M:$M,MATCH($A9,Baux!$A:$A,0)) | F9: =TEXT(VALUE(LEFT(INDEX(Baux!$N:$N,MATCH($A9,Baux!$A:$A,0)),4))+C9*INDEX(Baux!$O:$O,MATCH($A9,Baux!$A:$A,0)),"0")&RIGHT(INDEX(Baux!$N:$N,MATCH($A9,Baux!$A:$A,0)),3) | G9: =IF(SUMIFS(Indices!$C:$C,Indices!$A:$A,E9,Indices!$B:$B,F9)=0,"",SUMIFS(Indices!$C:$C,Indices!$A:$A,E9,Indices!$B:$B,F9)) | H9: =IF(INDEX(Baux!$P:$P,MATCH($A9,Baux!$A:$A,0))="Base fixe",INDEX(Baux!$N:$N,MATCH($A9,Baux!$A:$A,0)),IF(K8="Geler – rattrapage possible",H8,F8)) | I9: =IF(SUMIFS(Indices!$C:$C,Indices!$A:$A,E9,Indices!$B:$B,H9)=0,"",SUMIFS(Indices!$C:$C,Indices!$A:$A,E9,Indices!$B:$B,H9)) | J9: =IF(OR(G9="",I9=""),"",G9/I9) | L9: =IF(INDEX(Baux!$P:$P,MATCH($A9,Baux!$A:$A,0))="Base fixe",INDEX(Baux!$I:$I,MATCH($A9,Baux!$A:$A,0)),N8) | M9: =IF(OR(J9="",L9=""),"",ROUND(L9*J9,2)) | N9: =IF(LEFT(K9,5)="Geler",O9,IF(M9="","",IF(INDEX(Baux!$Q:$Q,MATCH($A9,Baux!$A:$A,0))="",M9,MIN(M9,ROUND(L9*(1+INDEX(Baux!$Q:$Q,MATCH($A9,Baux!$A:$A,0))/100)^IF(INDEX(Baux!$P:$P,MATCH($A9,Baux!$A:$A,0))="Base fixe",C9*INDEX(Baux!$O:$O,MATCH($A9,Baux!$A:$A,0)),VALUE(LEFT(F9,4))-VALUE(LEFT(H9,4))),2))))) | O9: =N8 | P9: =IF(OR(N9="",O9=""),"",N9/O9-1) | Q9: =IF(N9="","",N9/12) | R9: =IF(N9="","",N9/IF(INDEX(Baux!$L:$L,MATCH($A9,Baux!$A:$A,0))="Mensuelle",12,IF(INDEX(Baux!$L:$L,MATCH($A9,Baux!$A:$A,0))="Trimestrielle",4,IF(INDEX(Baux!$L:$L,MATCH($A9,Baux!$A:$A,0))="Semestrielle",2,1)))) | S9: =IF(INDEX(Baux!$J:$J,MATCH($A9,Baux!$A:$A,0))="",0,INDEX(Baux!$J:$J,MATCH($A9,Baux!$A:$A,0)))/IF(INDEX(Baux!$L:$L,MATCH($A9,Baux!$A:$A,0))="Mensuelle",12,IF(INDEX(Baux!$L:$L,MATCH($A9,Baux!$A:$A,0))="Trimestrielle",4,IF(INDEX(Baux!$L:$L,MATCH($A9,Baux!$A:$A,0))="Semestrielle",2,1))) | T9: =IF(R9="","",(R9+S9)*INDEX(Baux!$K:$K,MATCH($A9,Baux!$A:$A,0))/100) | U9: =IF(R9="","",R9+S9+T9) | V9: =IF(LEFT(K9,5)="Geler","❄ Gelée",IF(G9="",IF(D9<=TODAY(),"⚠ Indice attendu","À venir"),IF(D9<=TODAY(),"✔ Calculable","Indice connu – à venir"))) | AB9: =A9&"#"&C9 | AC9: =IF(AND(D9<=TODAY(),N9<>""),1,0)
A10: B01 | B10: =INDEX(Baux!$B:$B,MATCH($A10,Baux!$A:$A,0)) | C10: 9 | D10: =EDATE(INDEX(Baux!$F:$F,MATCH($A10,Baux!$A:$A,0)),12*INDEX(Baux!$O:$O,MATCH($A10,Baux!$A:$A,0))*C10) | E10: =INDEX(Baux!$M:$M,MATCH($A10,Baux!$A:$A,0)) | F10: =TEXT(VALUE(LEFT(INDEX(Baux!$N:$N,MATCH($A10,Baux!$A:$A,0)),4))+C10*INDEX(Baux!$O:$O,MATCH($A10,Baux!$A:$A,0)),"0")&RIGHT(INDEX(Baux!$N:$N,MATCH($A10,Baux!$A:$A,0)),3) | G10: =IF(SUMIFS(Indices!$C:$C,Indices!$A:$A,E10,Indices!$B:$B,F10)=0,"",SUMIFS(Indices!$C:$C,Indices!$A:$A,E10,Indices!$B:$B,F10)) | H10: =IF(INDEX(Baux!$P:$P,MATCH($A10,Baux!$A:$A,0))="Base fixe",INDEX(Baux!$N:$N,MATCH($A10,Baux!$A:$A,0)),IF(K9="Geler – rattrapage possible",H9,F9)) | I10: =IF(SUMIFS(Indices!$C:$C,Indices!$A:$A,E10,Indices!$B:$B,H10)=0,"",SUMIFS(Indices!$C:$C,Indices!$A:$A,E10,Indices!$B:$B,H10)) | J10: =IF(OR(G10="",I10=""),"",G10/I10) | L10: =IF(INDEX(Baux!$P:$P,MATCH($A10,Baux!$A:$A,0))="Base fixe",INDEX(Baux!$I:$I,MATCH($A10,Baux!$A:$A,0)),N9) | M10: =IF(OR(J10="",L10=""),"",ROUND(L10*J10,2)) | N10: =IF(LEFT(K10,5)="Geler",O10,IF(M10="","",IF(INDEX(Baux!$Q:$Q,MATCH($A10,Baux!$A:$A,0))="",M10,MIN(M10,ROUND(L10*(1+INDEX(Baux!$Q:$Q,MATCH($A10,Baux!$A:$A,0))/100)^IF(INDEX(Baux!$P:$P,MATCH($A10,Baux!$A:$A,0))="Base fixe",C10*INDEX(Baux!$O:$O,MATCH($A10,Baux!$A:$A,0)),VALUE(LEFT(F10,4))-VALUE(LEFT(H10,4))),2))))) | O10: =N9 | P10: =IF(OR(N10="",O10=""),"",N10/O10-1) | Q10: =IF(N10="","",N10/12) | R10: =IF(N10="","",N10/IF(INDEX(Baux!$L:$L,MATCH($A10,Baux!$A:$A,0))="Mensuelle",12,IF(INDEX(Baux!$L:$L,MATCH($A10,Baux!$A:$A,0))="Trimestrielle",4,IF(INDEX(Baux!$L:$L,MATCH($A10,Baux!$A:$A,0))="Semestrielle",2,1)))) | S10: =IF(INDEX(Baux!$J:$J,MATCH($A10,Baux!$A:$A,0))="",0,INDEX(Baux!$J:$J,MATCH($A10,Baux!$A:$A,0)))/IF(INDEX(Baux!$L:$L,MATCH($A10,Baux!$A:$A,0))="Mensuelle",12,IF(INDEX(Baux!$L:$L,MATCH($A10,Baux!$A:$A,0))="Trimestrielle",4,IF(INDEX(Baux!$L:$L,MATCH($A10,Baux!$A:$A,0))="Semestrielle",2,1))) | T10: =IF(R10="","",(R10+S10)*INDEX(Baux!$K:$K,MATCH($A10,Baux!$A:$A,0))/100) | U10: =IF(R10="","",R10+S10+T10) | V10: =IF(LEFT(K10,5)="Geler","❄ Gelée",IF(G10="",IF(D10<=TODAY(),"⚠ Indice attendu","À venir"),IF(D10<=TODAY(),"✔ Calculable","Indice connu – à venir"))) | AB10: =A10&"#"&C10 | AC10: =IF(AND(D10<=TODAY(),N10<>""),1,0)
A11: B02 | B11: =INDEX(Baux!$B:$B,MATCH($A11,Baux!$A:$A,0)) | C11: 1 | D11: =EDATE(INDEX(Baux!$F:$F,MATCH($A11,Baux!$A:$A,0)),12*INDEX(Baux!$O:$O,MATCH($A11,Baux!$A:$A,0))*C11) | E11: =INDEX(Baux!$M:$M,MATCH($A11,Baux!$A:$A,0)) | F11: =TEXT(VALUE(LEFT(INDEX(Baux!$N:$N,MATCH($A11,Baux!$A:$A,0)),4))+C11*INDEX(Baux!$O:$O,MATCH($A11,Baux!$A:$A,0)),"0")&RIGHT(INDEX(Baux!$N:$N,MATCH($A11,Baux!$A:$A,0)),3) | G11: =IF(SUMIFS(Indices!$C:$C,Indices!$A:$A,E11,Indices!$B:$B,F11)=0,"",SUMIFS(Indices!$C:$C,Indices!$A:$A,E11,Indices!$B:$B,F11)) | H11: =INDEX(Baux!$N:$N,MATCH($A11,Baux!$A:$A,0)) | I11: =IF(SUMIFS(Indices!$C:$C,Indices!$A:$A,E11,Indices!$B:$B,H11)=0,"",SUMIFS(Indices!$C:$C,Indices!$A:$A,E11,Indices!$B:$B,H11)) | J11: =IF(OR(G11="",I11=""),"",G11/I11) | L11: =INDEX(Baux!$I:$I,MATCH($A11,Baux!$A:$A,0)) | M11: =IF(OR(J11="",L11=""),"",ROUND(L11*J11,2)) | N11: =IF(LEFT(K11,5)="Geler",O11,IF(M11="","",IF(INDEX(Baux!$Q:$Q,MATCH($A11,Baux!$A:$A,0))="",M11,MIN(M11,ROUND(L11*(1+INDEX(Baux!$Q:$Q,MATCH($A11,Baux!$A:$A,0))/100)^IF(INDEX(Baux!$P:$P,MATCH($A11,Baux!$A:$A,0))="Base fixe",C11*INDEX(Baux!$O:$O,MATCH($A11,Baux!$A:$A,0)),VALUE(LEFT(F11,4))-VALUE(LEFT(H11,4))),2))))) | O11: =INDEX(Baux!$I:$I,MATCH($A11,Baux!$A:$A,0)) | P11: =IF(OR(N11="",O11=""),"",N11/O11-1) | Q11: =IF(N11="","",N11/12) | R11: =IF(N11="","",N11/IF(INDEX(Baux!$L:$L,MATCH($A11,Baux!$A:$A,0))="Mensuelle",12,IF(INDEX(Baux!$L:$L,MATCH($A11,Baux!$A:$A,0))="Trimestrielle",4,IF(INDEX(Baux!$L:$L,MATCH($A11,Baux!$A:$A,0))="Semestrielle",2,1)))) | S11: =IF(INDEX(Baux!$J:$J,MATCH($A11,Baux!$A:$A,0))="",0,INDEX(Baux!$J:$J,MATCH($A11,Baux!$A:$A,0)))/IF(INDEX(Baux!$L:$L,MATCH($A11,Baux!$A:$A,0))="Mensuelle",12,IF(INDEX(Baux!$L:$L,MATCH($A11,Baux!$A:$A,0))="Trimestrielle",4,IF(INDEX(Baux!$L:$L,MATCH($A11,Baux!$A:$A,0))="Semestrielle",2,1))) | T11: =IF(R11="","",(R11+S11)*INDEX(Baux!$K:$K,MATCH($A11,Baux!$A:$A,0))/100) | U11: =IF(R11="","",R11+S11+T11) | V11: =IF(LEFT(K11,5)="Geler","❄ Gelée",IF(G11="",IF(D11<=TODAY(),"⚠ Indice attendu","À venir"),IF(D11<=TODAY(),"✔ Calculable","Indice connu – à venir"))) | AB11: =A11&"#"&C11 | AC11: =IF(AND(D11<=TODAY(),N11<>""),1,0)
A12: B02 | B12: =INDEX(Baux!$B:$B,MATCH($A12,Baux!$A:$A,0)) | C12: 2 | D12: =EDATE(INDEX(Baux!$F:$F,MATCH($A12,Baux!$A:$A,0)),12*INDEX(Baux!$O:$O,MATCH($A12,Baux!$A:$A,0))*C12) | E12: =INDEX(Baux!$M:$M,MATCH($A12,Baux!$A:$A,0)) | F12: =TEXT(VALUE(LEFT(INDEX(Baux!$N:$N,MATCH($A12,Baux!$A:$A,0)),4))+C12*INDEX(Baux!$O:$O,MATCH($A12,Baux!$A:$A,0)),"0")&RIGHT(INDEX(Baux!$N:$N,MATCH($A12,Baux!$A:$A,0)),3) | G12: =IF(SUMIFS(Indices!$C:$C,Indices!$A:$A,E12,Indices!$B:$B,F12)=0,"",SUMIFS(Indices!$C:$C,Indices!$A:$A,E12,Indices!$B:$B,F12)) | H12: =IF(INDEX(Baux!$P:$P,MATCH($A12,Baux!$A:$A,0))="Base fixe",INDEX(Baux!$N:$N,MATCH($A12,Baux!$A:$A,0)),IF(K11="Geler – rattrapage possible",H11,F11)) | I12: =IF(SUMIFS(Indices!$C:$C,Indices!$A:$A,E12,Indices!$B:$B,H12)=0,"",SUMIFS(Indices!$C:$C,Indices!$A:$A,E12,Indices!$B:$B,H12)) | J12: =IF(OR(G12="",I12=""),"",G12/I12) | L12: =IF(INDEX(Baux!$P:$P,MATCH($A12,Baux!$A:$A,0))="Base fixe",INDEX(Baux!$I:$I,MATCH($A12,Baux!$A:$A,0)),N11) | M12: =IF(OR(J12="",L12=""),"",ROUND(L12*J12,2)) | N12: =IF(LEFT(K12,5)="Geler",O12,IF(M12="","",IF(INDEX(Baux!$Q:$Q,MATCH($A12,Baux!$A:$A,0))="",M12,MIN(M12,ROUND(L12*(1+INDEX(Baux!$Q:$Q,MATCH($A12,Baux!$A:$A,0))/100)^IF(INDEX(Baux!$P:$P,MATCH($A12,Baux!$A:$A,0))="Base fixe",C12*INDEX(Baux!$O:$O,MATCH($A12,Baux!$A:$A,0)),VALUE(LEFT(F12,4))-VALUE(LEFT(H12,4))),2))))) | O12: =N11 | P12: =IF(OR(N12="",O12=""),"",N12/O12-1) | Q12: =IF(N12="","",N12/12) | R12: =IF(N12="","",N12/IF(INDEX(Baux!$L:$L,MATCH($A12,Baux!$A:$A,0))="Mensuelle",12,IF(INDEX(Baux!$L:$L,MATCH($A12,Baux!$A:$A,0))="Trimestrielle",4,IF(INDEX(Baux!$L:$L,MATCH($A12,Baux!$A:$A,0))="Semestrielle",2,1)))) | S12: =IF(INDEX(Baux!$J:$J,MATCH($A12,Baux!$A:$A,0))="",0,INDEX(Baux!$J:$J,MATCH($A12,Baux!$A:$A,0)))/IF(INDEX(Baux!$L:$L,MATCH($A12,Baux!$A:$A,0))="Mensuelle",12,IF(INDEX(Baux!$L:$L,MATCH($A12,Baux!$A:$A,0))="Trimestrielle",4,IF(INDEX(Baux!$L:$L,MATCH($A12,Baux!$A:$A,0))="Semestrielle",2,1))) | T12: =IF(R12="","",(R12+S12)*INDEX(Baux!$K:$K,MATCH($A12,Baux!$A:$A,0))/100) | U12: =IF(R12="","",R12+S12+T12) | V12: =IF(LEFT(K12,5)="Geler","❄ Gelée",IF(G12="",IF(D12<=TODAY(),"⚠ Indice attendu","À venir"),IF(D12<=TODAY(),"✔ Calculable","Indice connu – à venir"))) | AB12: =A12&"#"&C12 | AC12: =IF(AND(D12<=TODAY(),N12<>""),1,0)
A13: B02 | B13: =INDEX(Baux!$B:$B,MATCH($A13,Baux!$A:$A,0)) | C13: 3 | D13: =EDATE(INDEX(Baux!$F:$F,MATCH($A13,Baux!$A:$A,0)),12*INDEX(Baux!$O:$O,MATCH($A13,Baux!$A:$A,0))*C13) | E13: =INDEX(Baux!$M:$M,MATCH($A13,Baux!$A:$A,0)) | F13: =TEXT(VALUE(LEFT(INDEX(Baux!$N:$N,MATCH($A13,Baux!$A:$A,0)),4))+C13*INDEX(Baux!$O:$O,MATCH($A13,Baux!$A:$A,0)),"0")&RIGHT(INDEX(Baux!$N:$N,MATCH($A13,Baux!$A:$A,0)),3) | G13: =IF(SUMIFS(Indices!$C:$C,Indices!$A:$A,E13,Indices!$B:$B,F13)=0,"",SUMIFS(Indices!$C:$C,Indices!$A:$A,E13,Indices!$B:$B,F13)) | H13: =IF(INDEX(Baux!$P:$P,MATCH($A13,Baux!$A:$A,0))="Base fixe",INDEX(Baux!$N:$N,MATCH($A13,Baux!$A:$A,0)),IF(K12="Geler – rattrapage possible",H12,F12)) | I13: =IF(SUMIFS(Indices!$C:$C,Indices!$A:$A,E13,Indices!$B:$B,H13)=0,"",SUMIFS(Indices!$C:$C,Indices!$A:$A,E13,Indices!$B:$B,H13)) | J13: =IF(OR(G13="",I13=""),"",G13/I13) | L13: =IF(INDEX(Baux!$P:$P,MATCH($A13,Baux!$A:$A,0))="Base fixe",INDEX(Baux!$I:$I,MATCH($A13,Baux!$A:$A,0)),N12) | M13: =IF(OR(J13="",L13=""),"",ROUND(L13*J13,2)) | N13: =IF(LEFT(K13,5)="Geler",O13,IF(M13="","",IF(INDEX(Baux!$Q:$Q,MATCH($A13,Baux!$A:$A,0))="",M13,MIN(M13,ROUND(L13*(1+INDEX(Baux!$Q:$Q,MATCH($A13,Baux!$A:$A,0))/100)^IF(INDEX(Baux!$P:$P,MATCH($A13,Baux!$A:$A,0))="Base fixe",C13*INDEX(Baux!$O:$O,MATCH($A13,Baux!$A:$A,0)),VALUE(LEFT(F13,4))-VALUE(LEFT(H13,4))),2))))) | O13: =N12 | P13: =IF(OR(N13="",O13=""),"",N13/O13-1) | Q13: =IF(N13="","",N13/12) | R13: =IF(N13="","",N13/IF(INDEX(Baux!$L:$L,MATCH($A13,Baux!$A:$A,0))="Mensuelle",12,IF(INDEX(Baux!$L:$L,MATCH($A13,Baux!$A:$A,0))="Trimestrielle",4,IF(INDEX(Baux!$L:$L,MATCH($A13,Baux!$A:$A,0))="Semestrielle",2,1)))) | S13: =IF(INDEX(Baux!$J:$J,MATCH($A13,Baux!$A:$A,0))="",0,INDEX(Baux!$J:$J,MATCH($A13,Baux!$A:$A,0)))/IF(INDEX(Baux!$L:$L,MATCH($A13,Baux!$A:$A,0))="Mensuelle",12,IF(INDEX(Baux!$L:$L,MATCH($A13,Baux!$A:$A,0))="Trimestrielle",4,IF(INDEX(Baux!$L:$L,MATCH($A13,Baux!$A:$A,0))="Semestrielle",2,1))) | T13: =IF(R13="","",(R13+S13)*INDEX(Baux!$K:$K,MATCH($A13,Baux!$A:$A,0))/100) | U13: =IF(R13="","",R13+S13+T13) | V13: =IF(LEFT(K13,5)="Geler","❄ Gelée",IF(G13="",IF(D13<=TODAY(),"⚠ Indice attendu","À venir"),IF(D13<=TODAY(),"✔ Calculable","Indice connu – à venir"))) | AB13: =A13&"#"&C13 | AC13: =IF(AND(D13<=TODAY(),N13<>""),1,0)
A14: B03 | B14: =INDEX(Baux!$B:$B,MATCH($A14,Baux!$A:$A,0)) | C14: 1 | D14: =EDATE(INDEX(Baux!$F:$F,MATCH($A14,Baux!$A:$A,0)),12*INDEX(Baux!$O:$O,MATCH($A14,Baux!$A:$A,0))*C14) | E14: =INDEX(Baux!$M:$M,MATCH($A14,Baux!$A:$A,0)) | F14: =TEXT(VALUE(LEFT(INDEX(Baux!$N:$N,MATCH($A14,Baux!$A:$A,0)),4))+C14*INDEX(Baux!$O:$O,MATCH($A14,Baux!$A:$A,0)),"0")&RIGHT(INDEX(Baux!$N:$N,MATCH($A14,Baux!$A:$A,0)),3) | G14: =IF(SUMIFS(Indices!$C:$C,Indices!$A:$A,E14,Indices!$B:$B,F14)=0,"",SUMIFS(Indices!$C:$C,Indices!$A:$A,E14,Indices!$B:$B,F14)) | H14: =INDEX(Baux!$N:$N,MATCH($A14,Baux!$A:$A,0)) | I14: =IF(SUMIFS(Indices!$C:$C,Indices!$A:$A,E14,Indices!$B:$B,H14)=0,"",SUMIFS(Indices!$C:$C,Indices!$A:$A,E14,Indices!$B:$B,H14)) | J14: =IF(OR(G14="",I14=""),"",G14/I14) | L14: =INDEX(Baux!$I:$I,MATCH($A14,Baux!$A:$A,0)) | M14: =IF(OR(J14="",L14=""),"",ROUND(L14*J14,2)) | N14: =IF(LEFT(K14,5)="Geler",O14,IF(M14="","",IF(INDEX(Baux!$Q:$Q,MATCH($A14,Baux!$A:$A,0))="",M14,MIN(M14,ROUND(L14*(1+INDEX(Baux!$Q:$Q,MATCH($A14,Baux!$A:$A,0))/100)^IF(INDEX(Baux!$P:$P,MATCH($A14,Baux!$A:$A,0))="Base fixe",C14*INDEX(Baux!$O:$O,MATCH($A14,Baux!$A:$A,0)),VALUE(LEFT(F14,4))-VALUE(LEFT(H14,4))),2))))) | O14: =INDEX(Baux!$I:$I,MATCH($A14,Baux!$A:$A,0)) | P14: =IF(OR(N14="",O14=""),"",N14/O14-1) | Q14: =IF(N14="","",N14/12) | R14: =IF(N14="","",N14/IF(INDEX(Baux!$L:$L,MATCH($A14,Baux!$A:$A,0))="Mensuelle",12,IF(INDEX(Baux!$L:$L,MATCH($A14,Baux!$A:$A,0))="Trimestrielle",4,IF(INDEX(Baux!$L:$L,MATCH($A14,Baux!$A:$A,0))="Semestrielle",2,1)))) | S14: =IF(INDEX(Baux!$J:$J,MATCH($A14,Baux!$A:$A,0))="",0,INDEX(Baux!$J:$J,MATCH($A14,Baux!$A:$A,0)))/IF(INDEX(Baux!$L:$L,MATCH($A14,Baux!$A:$A,0))="Mensuelle",12,IF(INDEX(Baux!$L:$L,MATCH($A14,Baux!$A:$A,0))="Trimestrielle",4,IF(INDEX(Baux!$L:$L,MATCH($A14,Baux!$A:$A,0))="Semestrielle",2,1))) | T14: =IF(R14="","",(R14+S14)*INDEX(Baux!$K:$K,MATCH($A14,Baux!$A:$A,0))/100) | U14: =IF(R14="","",R14+S14+T14) | V14: =IF(LEFT(K14,5)="Geler","❄ Gelée",IF(G14="",IF(D14<=TODAY(),"⚠ Indice attendu","À venir"),IF(D14<=TODAY(),"✔ Calculable","Indice connu – à venir"))) | X14: Oui | AB14: =A14&"#"&C14 | AC14: =IF(AND(D14<=TODAY(),N14<>""),1,0)
A15: B03 | B15: =INDEX(Baux!$B:$B,MATCH($A15,Baux!$A:$A,0)) | C15: 2 | D15: =EDATE(INDEX(Baux!$F:$F,MATCH($A15,Baux!$A:$A,0)),12*INDEX(Baux!$O:$O,MATCH($A15,Baux!$A:$A,0))*C15) | E15: =INDEX(Baux!$M:$M,MATCH($A15,Baux!$A:$A,0)) | F15: =TEXT(VALUE(LEFT(INDEX(Baux!$N:$N,MATCH($A15,Baux!$A:$A,0)),4))+C15*INDEX(Baux!$O:$O,MATCH($A15,Baux!$A:$A,0)),"0")&RIGHT(INDEX(Baux!$N:$N,MATCH($A15,Baux!$A:$A,0)),3) | G15: =IF(SUMIFS(Indices!$C:$C,Indices!$A:$A,E15,Indices!$B:$B,F15)=0,"",SUMIFS(Indices!$C:$C,Indices!$A:$A,E15,Indices!$B:$B,F15)) | H15: =IF(INDEX(Baux!$P:$P,MATCH($A15,Baux!$A:$A,0))="Base fixe",INDEX(Baux!$N:$N,MATCH($A15,Baux!$A:$A,0)),IF(K14="Geler – rattrapage possible",H14,F14)) | I15: =IF(SUMIFS(Indices!$C:$C,Indices!$A:$A,E15,Indices!$B:$B,H15)=0,"",SUMIFS(Indices!$C:$C,Indices!$A:$A,E15,Indices!$B:$B,H15)) | J15: =IF(OR(G15="",I15=""),"",G15/I15) | L15: =IF(INDEX(Baux!$P:$P,MATCH($A15,Baux!$A:$A,0))="Base fixe",INDEX(Baux!$I:$I,MATCH($A15,Baux!$A:$A,0)),N14) | M15: =IF(OR(J15="",L15=""),"",ROUND(L15*J15,2)) | N15: =IF(LEFT(K15,5)="Geler",O15,IF(M15="","",IF(INDEX(Baux!$Q:$Q,MATCH($A15,Baux!$A:$A,0))="",M15,MIN(M15,ROUND(L15*(1+INDEX(Baux!$Q:$Q,MATCH($A15,Baux!$A:$A,0))/100)^IF(INDEX(Baux!$P:$P,MATCH($A15,Baux!$A:$A,0))="Base fixe",C15*INDEX(Baux!$O:$O,MATCH($A15,Baux!$A:$A,0)),VALUE(LEFT(F15,4))-VALUE(LEFT(H15,4))),2))))) | O15: =N14 | P15: =IF(OR(N15="",O15=""),"",N15/O15-1) | Q15: =IF(N15="","",N15/12) | R15: =IF(N15="","",N15/IF(INDEX(Baux!$L:$L,MATCH($A15,Baux!$A:$A,0))="Mensuelle",12,IF(INDEX(Baux!$L:$L,MATCH($A15,Baux!$A:$A,0))="Trimestrielle",4,IF(INDEX(Baux!$L:$L,MATCH($A15,Baux!$A:$A,0))="Semestrielle",2,1)))) | S15: =IF(INDEX(Baux!$J:$J,MATCH($A15,Baux!$A:$A,0))="",0,INDEX(Baux!$J:$J,MATCH($A15,Baux!$A:$A,0)))/IF(INDEX(Baux!$L:$L,MATCH($A15,Baux!$A:$A,0))="Mensuelle",12,IF(INDEX(Baux!$L:$L,MATCH($A15,Baux!$A:$A,0))="Trimestrielle",4,IF(INDEX(Baux!$L:$L,MATCH($A15,Baux!$A:$A,0))="Semestrielle",2,1))) | T15: =IF(R15="","",(R15+S15)*INDEX(Baux!$K:$K,MATCH($A15,Baux!$A:$A,0))/100) | U15: =IF(R15="","",R15+S15+T15) | V15: =IF(LEFT(K15,5)="Geler","❄ Gelée",IF(G15="",IF(D15<=TODAY(),"⚠ Indice attendu","À venir"),IF(D15<=TODAY(),"✔ Calculable","Indice connu – à venir"))) | X15: Oui | AB15: =A15&"#"&C15 | AC15: =IF(AND(D15<=TODAY(),N15<>""),1,0)
A16: B03 | B16: =INDEX(Baux!$B:$B,MATCH($A16,Baux!$A:$A,0)) | C16: 3 | D16: =EDATE(INDEX(Baux!$F:$F,MATCH($A16,Baux!$A:$A,0)),12*INDEX(Baux!$O:$O,MATCH($A16,Baux!$A:$A,0))*C16) | E16: =INDEX(Baux!$M:$M,MATCH($A16,Baux!$A:$A,0)) | F16: =TEXT(VALUE(LEFT(INDEX(Baux!$N:$N,MATCH($A16,Baux!$A:$A,0)),4))+C16*INDEX(Baux!$O:$O,MATCH($A16,Baux!$A:$A,0)),"0")&RIGHT(INDEX(Baux!$N:$N,MATCH($A16,Baux!$A:$A,0)),3) | G16: =IF(SUMIFS(Indices!$C:$C,Indices!$A:$A,E16,Indices!$B:$B,F16)=0,"",SUMIFS(Indices!$C:$C,Indices!$A:$A,E16,Indices!$B:$B,F16)) | H16: =IF(INDEX(Baux!$P:$P,MATCH($A16,Baux!$A:$A,0))="Base fixe",INDEX(Baux!$N:$N,MATCH($A16,Baux!$A:$A,0)),IF(K15="Geler – rattrapage possible",H15,F15)) | I16: =IF(SUMIFS(Indices!$C:$C,Indices!$A:$A,E16,Indices!$B:$B,H16)=0,"",SUMIFS(Indices!$C:$C,Indices!$A:$A,E16,Indices!$B:$B,H16)) | J16: =IF(OR(G16="",I16=""),"",G16/I16) | L16: =IF(INDEX(Baux!$P:$P,MATCH($A16,Baux!$A:$A,0))="Base fixe",INDEX(Baux!$I:$I,MATCH($A16,Baux!$A:$A,0)),N15) | M16: =IF(OR(J16="",L16=""),"",ROUND(L16*J16,2)) | N16: =IF(LEFT(K16,5)="Geler",O16,IF(M16="","",IF(INDEX(Baux!$Q:$Q,MATCH($A16,Baux!$A:$A,0))="",M16,MIN(M16,ROUND(L16*(1+INDEX(Baux!$Q:$Q,MATCH($A16,Baux!$A:$A,0))/100)^IF(INDEX(Baux!$P:$P,MATCH($A16,Baux!$A:$A,0))="Base fixe",C16*INDEX(Baux!$O:$O,MATCH($A16,Baux!$A:$A,0)),VALUE(LEFT(F16,4))-VALUE(LEFT(H16,4))),2))))) | O16: =N15 | P16: =IF(OR(N16="",O16=""),"",N16/O16-1) | Q16: =IF(N16="","",N16/12) | R16: =IF(N16="","",N16/IF(INDEX(Baux!$L:$L,MATCH($A16,Baux!$A:$A,0))="Mensuelle",12,IF(INDEX(Baux!$L:$L,MATCH($A16,Baux!$A:$A,0))="Trimestrielle",4,IF(INDEX(Baux!$L:$L,MATCH($A16,Baux!$A:$A,0))="Semestrielle",2,1)))) | S16: =IF(INDEX(Baux!$J:$J,MATCH($A16,Baux!$A:$A,0))="",0,INDEX(Baux!$J:$J,MATCH($A16,Baux!$A:$A,0)))/IF(INDEX(Baux!$L:$L,MATCH($A16,Baux!$A:$A,0))="Mensuelle",12,IF(INDEX(Baux!$L:$L,MATCH($A16,Baux!$A:$A,0))="Trimestrielle",4,IF(INDEX(Baux!$L:$L,MATCH($A16,Baux!$A:$A,0))="Semestrielle",2,1))) | T16: =IF(R16="","",(R16+S16)*INDEX(Baux!$K:$K,MATCH($A16,Baux!$A:$A,0))/100) | U16: =IF(R16="","",R16+S16+T16) | V16: =IF(LEFT(K16,5)="Geler","❄ Gelée",IF(G16="",IF(D16<=TODAY(),"⚠ Indice attendu","À venir"),IF(D16<=TODAY(),"✔ Calculable","Indice connu – à venir"))) | X16: Oui | AB16: =A16&"#"&C16 | AC16: =IF(AND(D16<=TODAY(),N16<>""),1,0)
A17: B03 | B17: =INDEX(Baux!$B:$B,MATCH($A17,Baux!$A:$A,0)) | C17: 4 | D17: =EDATE(INDEX(Baux!$F:$F,MATCH($A17,Baux!$A:$A,0)),12*INDEX(Baux!$O:$O,MATCH($A17,Baux!$A:$A,0))*C17) | E17: =INDEX(Baux!$M:$M,MATCH($A17,Baux!$A:$A,0)) | F17: =TEXT(VALUE(LEFT(INDEX(Baux!$N:$N,MATCH($A17,Baux!$A:$A,0)),4))+C17*INDEX(Baux!$O:$O,MATCH($A17,Baux!$A:$A,0)),"0")&RIGHT(INDEX(Baux!$N:$N,MATCH($A17,Baux!$A:$A,0)),3) | G17: =IF(SUMIFS(Indices!$C:$C,Indices!$A:$A,E17,Indices!$B:$B,F17)=0,"",SUMIFS(Indices!$C:$C,Indices!$A:$A,E17,Indices!$B:$B,F17)) | H17: =IF(INDEX(Baux!$P:$P,MATCH($A17,Baux!$A:$A,0))="Base fixe",INDEX(Baux!$N:$N,MATCH($A17,Baux!$A:$A,0)),IF(K16="Geler – rattrapage possible",H16,F16)) | I17: =IF(SUMIFS(Indices!$C:$C,Indices!$A:$A,E17,Indices!$B:$B,H17)=0,"",SUMIFS(Indices!$C:$C,Indices!$A:$A,E17,Indices!$B:$B,H17)) | J17: =IF(OR(G17="",I17=""),"",G17/I17) | L17: =IF(INDEX(Baux!$P:$P,MATCH($A17,Baux!$A:$A,0))="Base fixe",INDEX(Baux!$I:$I,MATCH($A17,Baux!$A:$A,0)),N16) | M17: =IF(OR(J17="",L17=""),"",ROUND(L17*J17,2)) | N17: =IF(LEFT(K17,5)="Geler",O17,IF(M17="","",IF(INDEX(Baux!$Q:$Q,MATCH($A17,Baux!$A:$A,0))="",M17,MIN(M17,ROUND(L17*(1+INDEX(Baux!$Q:$Q,MATCH($A17,Baux!$A:$A,0))/100)^IF(INDEX(Baux!$P:$P,MATCH($A17,Baux!$A:$A,0))="Base fixe",C17*INDEX(Baux!$O:$O,MATCH($A17,Baux!$A:$A,0)),VALUE(LEFT(F17,4))-VALUE(LEFT(H17,4))),2))))) | O17: =N16 | P17: =IF(OR(N17="",O17=""),"",N17/O17-1) | Q17: =IF(N17="","",N17/12) | R17: =IF(N17="","",N17/IF(INDEX(Baux!$L:$L,MATCH($A17,Baux!$A:$A,0))="Mensuelle",12,IF(INDEX(Baux!$L:$L,MATCH($A17,Baux!$A:$A,0))="Trimestrielle",4,IF(INDEX(Baux!$L:$L,MATCH($A17,Baux!$A:$A,0))="Semestrielle",2,1)))) | S17: =IF(INDEX(Baux!$J:$J,MATCH($A17,Baux!$A:$A,0))="",0,INDEX(Baux!$J:$J,MATCH($A17,Baux!$A:$A,0)))/IF(INDEX(Baux!$L:$L,MATCH($A17,Baux!$A:$A,0))="Mensuelle",12,IF(INDEX(Baux!$L:$L,MATCH($A17,Baux!$A:$A,0))="Trimestrielle",4,IF(INDEX(Baux!$L:$L,MATCH($A17,Baux!$A:$A,0))="Semestrielle",2,1))) | T17: =IF(R17="","",(R17+S17)*INDEX(Baux!$K:$K,MATCH($A17,Baux!$A:$A,0))/100) | U17: =IF(R17="","",R17+S17+T17) | V17: =IF(LEFT(K17,5)="Geler","❄ Gelée",IF(G17="",IF(D17<=TODAY(),"⚠ Indice attendu","À venir"),IF(D17<=TODAY(),"✔ Calculable","Indice connu – à venir"))) | X17: Oui | AB17: =A17&"#"&C17 | AC17: =IF(AND(D17<=TODAY(),N17<>""),1,0)
A18: B03 | B18: =INDEX(Baux!$B:$B,MATCH($A18,Baux!$A:$A,0)) | C18: 5 | D18: =EDATE(INDEX(Baux!$F:$F,MATCH($A18,Baux!$A:$A,0)),12*INDEX(Baux!$O:$O,MATCH($A18,Baux!$A:$A,0))*C18) | E18: =INDEX(Baux!$M:$M,MATCH($A18,Baux!$A:$A,0)) | F18: =TEXT(VALUE(LEFT(INDEX(Baux!$N:$N,MATCH($A18,Baux!$A:$A,0)),4))+C18*INDEX(Baux!$O:$O,MATCH($A18,Baux!$A:$A,0)),"0")&RIGHT(INDEX(Baux!$N:$N,MATCH($A18,Baux!$A:$A,0)),3) | G18: =IF(SUMIFS(Indices!$C:$C,Indices!$A:$A,E18,Indices!$B:$B,F18)=0,"",SUMIFS(Indices!$C:$C,Indices!$A:$A,E18,Indices!$B:$B,F18)) | H18: =IF(INDEX(Baux!$P:$P,MATCH($A18,Baux!$A:$A,0))="Base fixe",INDEX(Baux!$N:$N,MATCH($A18,Baux!$A:$A,0)),IF(K17="Geler – rattrapage possible",H17,F17)) | I18: =IF(SUMIFS(Indices!$C:$C,Indices!$A:$A,E18,Indices!$B:$B,H18)=0,"",SUMIFS(Indices!$C:$C,Indices!$A:$A,E18,Indices!$B:$B,H18)) | J18: =IF(OR(G18="",I18=""),"",G18/I18) | L18: =IF(INDEX(Baux!$P:$P,MATCH($A18,Baux!$A:$A,0))="Base fixe",INDEX(Baux!$I:$I,MATCH($A18,Baux!$A:$A,0)),N17) | M18: =IF(OR(J18="",L18=""),"",ROUND(L18*J18,2)) | N18: =IF(LEFT(K18,5)="Geler",O18,IF(M18="","",IF(INDEX(Baux!$Q:$Q,MATCH($A18,Baux!$A:$A,0))="",M18,MIN(M18,ROUND(L18*(1+INDEX(Baux!$Q:$Q,MATCH($A18,Baux!$A:$A,0))/100)^IF(INDEX(Baux!$P:$P,MATCH($A18,Baux!$A:$A,0))="Base fixe",C18*INDEX(Baux!$O:$O,MATCH($A18,Baux!$A:$A,0)),VALUE(LEFT(F18,4))-VALUE(LEFT(H18,4))),2))))) | O18: =N17 | P18: =IF(OR(N18="",O18=""),"",N18/O18-1) | Q18: =IF(N18="","",N18/12) | R18: =IF(N18="","",N18/IF(INDEX(Baux!$L:$L,MATCH($A18,Baux!$A:$A,0))="Mensuelle",12,IF(INDEX(Baux!$L:$L,MATCH($A18,Baux!$A:$A,0))="Trimestrielle",4,IF(INDEX(Baux!$L:$L,MATCH($A18,Baux!$A:$A,0))="Semestrielle",2,1)))) | S18: =IF(INDEX(Baux!$J:$J,MATCH($A18,Baux!$A:$A,0))="",0,INDEX(Baux!$J:$J,MATCH($A18,Baux!$A:$A,0)))/IF(INDEX(Baux!$L:$L,MATCH($A18,Baux!$A:$A,0))="Mensuelle",12,IF(INDEX(Baux!$L:$L,MATCH($A18,Baux!$A:$A,0))="Trimestrielle",4,IF(INDEX(Baux!$L:$L,MATCH($A18,Baux!$A:$A,0))="Semestrielle",2,1))) | T18: =IF(R18="","",(R18+S18)*INDEX(Baux!$K:$K,MATCH($A18,Baux!$A:$A,0))/100) | U18: =IF(R18="","",R18+S18+T18) | V18: =IF(LEFT(K18,5)="Geler","❄ Gelée",IF(G18="",IF(D18<=TODAY(),"⚠ Indice attendu","À venir"),IF(D18<=TODAY(),"✔ Calculable","Indice connu – à venir"))) | X18: Oui | AB18: =A18&"#"&C18 | AC18: =IF(AND(D18<=TODAY(),N18<>""),1,0)
A19: B03 | B19: =INDEX(Baux!$B:$B,MATCH($A19,Baux!$A:$A,0)) | C19: 6 | D19: =EDATE(INDEX(Baux!$F:$F,MATCH($A19,Baux!$A:$A,0)),12*INDEX(Baux!$O:$O,MATCH($A19,Baux!$A:$A,0))*C19) | E19: =INDEX(Baux!$M:$M,MATCH($A19,Baux!$A:$A,0)) | F19: =TEXT(VALUE(LEFT(INDEX(Baux!$N:$N,MATCH($A19,Baux!$A:$A,0)),4))+C19*INDEX(Baux!$O:$O,MATCH($A19,Baux!$A:$A,0)),"0")&RIGHT(INDEX(Baux!$N:$N,MATCH($A19,Baux!$A:$A,0)),3) | G19: =IF(SUMIFS(Indices!$C:$C,Indices!$A:$A,E19,Indices!$B:$B,F19)=0,"",SUMIFS(Indices!$C:$C,Indices!$A:$A,E19,Indices!$B:$B,F19)) | H19: =IF(INDEX(Baux!$P:$P,MATCH($A19,Baux!$A:$A,0))="Base fixe",INDEX(Baux!$N:$N,MATCH($A19,Baux!$A:$A,0)),IF(K18="Geler – rattrapage possible",H18,F18)) | I19: =IF(SUMIFS(Indices!$C:$C,Indices!$A:$A,E19,Indices!$B:$B,H19)=0,"",SUMIFS(Indices!$C:$C,Indices!$A:$A,E19,Indices!$B:$B,H19)) | J19: =IF(OR(G19="",I19=""),"",G19/I19) | K19: Geler – rattrapage possible | L19: =IF(INDEX(Baux!$P:$P,MATCH($A19,Baux!$A:$A,0))="Base fixe",INDEX(Baux!$I:$I,MATCH($A19,Baux!$A:$A,0)),N18) | M19: =IF(OR(J19="",L19=""),"",ROUND(L19*J19,2)) | N19: =IF(LEFT(K19,5)="Geler",O19,IF(M19="","",IF(INDEX(Baux!$Q:$Q,MATCH($A19,Baux!$A:$A,0))="",M19,MIN(M19,ROUND(L19*(1+INDEX(Baux!$Q:$Q,MATCH($A19,Baux!$A:$A,0))/100)^IF(INDEX(Baux!$P:$P,MATCH($A19,Baux!$A:$A,0))="Base fixe",C19*INDEX(Baux!$O:$O,MATCH($A19,Baux!$A:$A,0)),VALUE(LEFT(F19,4))-VALUE(LEFT(H19,4))),2))))) | O19: =N18 | P19: =IF(OR(N19="",O19=""),"",N19/O19-1) | Q19: =IF(N19="","",N19/12) | R19: =IF(N19="","",N19/IF(INDEX(Baux!$L:$L,MATCH($A19,Baux!$A:$A,0))="Mensuelle",12,IF(INDEX(Baux!$L:$L,MATCH($A19,Baux!$A:$A,0))="Trimestrielle",4,IF(INDEX(Baux!$L:$L,MATCH($A19,Baux!$A:$A,0))="Semestrielle",2,1)))) | S19: =IF(INDEX(Baux!$J:$J,MATCH($A19,Baux!$A:$A,0))="",0,INDEX(Baux!$J:$J,MATCH($A19,Baux!$A:$A,0)))/IF(INDEX(Baux!$L:$L,MATCH($A19,Baux!$A:$A,0))="Mensuelle",12,IF(INDEX(Baux!$L:$L,MATCH($A19,Baux!$A:$A,0))="Trimestrielle",4,IF(INDEX(Baux!$L:$L,MATCH($A19,Baux!$A:$A,0))="Semestrielle",2,1))) | T19: =IF(R19="","",(R19+S19)*INDEX(Baux!$K:$K,MATCH($A19,Baux!$A:$A,0))/100) | U19: =IF(R19="","",R19+S19+T19) | V19: =IF(LEFT(K19,5)="Geler","❄ Gelée",IF(G19="",IF(D19<=TODAY(),"⚠ Indice attendu","À venir"),IF(D19<=TODAY(),"✔ Calculable","Indice connu – à venir"))) | W19: Gel d'un an négocié (avenant du 10/01/2025), rattrapage à la révision 2026 : recalculer sur l'indice 2023-T3. | AB19: =A19&"#"&C19 | AC19: =IF(AND(D19<=TODAY(),N19<>""),1,0)
A20: B03 | B20: =INDEX(Baux!$B:$B,MATCH($A20,Baux!$A:$A,0)) | C20: 7 | D20: =EDATE(INDEX(Baux!$F:$F,MATCH($A20,Baux!$A:$A,0)),12*INDEX(Baux!$O:$O,MATCH($A20,Baux!$A:$A,0))*C20) | E20: =INDEX(Baux!$M:$M,MATCH($A20,Baux!$A:$A,0)) | F20: =TEXT(VALUE(LEFT(INDEX(Baux!$N:$N,MATCH($A20,Baux!$A:$A,0)),4))+C20*INDEX(Baux!$O:$O,MATCH($A20,Baux!$A:$A,0)),"0")&RIGHT(INDEX(Baux!$N:$N,MATCH($A20,Baux!$A:$A,0)),3) | G20: =IF(SUMIFS(Indices!$C:$C,Indices!$A:$A,E20,Indices!$B:$B,F20)=0,"",SUMIFS(Indices!$C:$C,Indices!$A:$A,E20,Indices!$B:$B,F20)) | H20: =IF(INDEX(Baux!$P:$P,MATCH($A20,Baux!$A:$A,0))="Base fixe",INDEX(Baux!$N:$N,MATCH($A20,Baux!$A:$A,0)),IF(K19="Geler – rattrapage possible",H19,F19)) | I20: =IF(SUMIFS(Indices!$C:$C,Indices!$A:$A,E20,Indices!$B:$B,H20)=0,"",SUMIFS(Indices!$C:$C,Indices!$A:$A,E20,Indices!$B:$B,H20)) | J20: =IF(OR(G20="",I20=""),"",G20/I20) | L20: =IF(INDEX(Baux!$P:$P,MATCH($A20,Baux!$A:$A,0))="Base fixe",INDEX(Baux!$I:$I,MATCH($A20,Baux!$A:$A,0)),N19) | M20: =IF(OR(J20="",L20=""),"",ROUND(L20*J20,2)) | N20: =IF(LEFT(K20,5)="Geler",O20,IF(M20="","",IF(INDEX(Baux!$Q:$Q,MATCH($A20,Baux!$A:$A,0))="",M20,MIN(M20,ROUND(L20*(1+INDEX(Baux!$Q:$Q,MATCH($A20,Baux!$A:$A,0))/100)^IF(INDEX(Baux!$P:$P,MATCH($A20,Baux!$A:$A,0))="Base fixe",C20*INDEX(Baux!$O:$O,MATCH($A20,Baux!$A:$A,0)),VALUE(LEFT(F20,4))-VALUE(LEFT(H20,4))),2))))) | O20: =N19 | P20: =IF(OR(N20="",O20=""),"",N20/O20-1) | Q20: =IF(N20="","",N20/12) | R20: =IF(N20="","",N20/IF(INDEX(Baux!$L:$L,MATCH($A20,Baux!$A:$A,0))="Mensuelle",12,IF(INDEX(Baux!$L:$L,MATCH($A20,Baux!$A:$A,0))="Trimestrielle",4,IF(INDEX(Baux!$L:$L,MATCH($A20,Baux!$A:$A,0))="Semestrielle",2,1)))) | S20: =IF(INDEX(Baux!$J:$J,MATCH($A20,Baux!$A:$A,0))="",0,INDEX(Baux!$J:$J,MATCH($A20,Baux!$A:$A,0)))/IF(INDEX(Baux!$L:$L,MATCH($A20,Baux!$A:$A,0))="Mensuelle",12,IF(INDEX(Baux!$L:$L,MATCH($A20,Baux!$A:$A,0))="Trimestrielle",4,IF(INDEX(Baux!$L:$L,MATCH($A20,Baux!$A:$A,0))="Semestrielle",2,1))) | T20: =IF(R20="","",(R20+S20)*INDEX(Baux!$K:$K,MATCH($A20,Baux!$A:$A,0))/100) | U20: =IF(R20="","",R20+S20+T20) | V20: =IF(LEFT(K20,5)="Geler","❄ Gelée",IF(G20="",IF(D20<=TODAY(),"⚠ Indice attendu","À venir"),IF(D20<=TODAY(),"✔ Calculable","Indice connu – à venir"))) | W20: Appliquer le rattrapage : coefficient calculé sur 2 ans d'indice. Prévenir le locataire avant facturation. | AB20: =A20&"#"&C20 | AC20: =IF(AND(D20<=TODAY(),N20<>""),1,0)
A21: B03 | B21: =INDEX(Baux!$B:$B,MATCH($A21,Baux!$A:$A,0)) | C21: 8 | D21: =EDATE(INDEX(Baux!$F:$F,MATCH($A21,Baux!$A:$A,0)),12*INDEX(Baux!$O:$O,MATCH($A21,Baux!$A:$A,0))*C21) | E21: =INDEX(Baux!$M:$M,MATCH($A21,Baux!$A:$A,0)) | F21: =TEXT(VALUE(LEFT(INDEX(Baux!$N:$N,MATCH($A21,Baux!$A:$A,0)),4))+C21*INDEX(Baux!$O:$O,MATCH($A21,Baux!$A:$A,0)),"0")&RIGHT(INDEX(Baux!$N:$N,MATCH($A21,Baux!$A:$A,0)),3) | G21: =IF(SUMIFS(Indices!$C:$C,Indices!$A:$A,E21,Indices!$B:$B,F21)=0,"",SUMIFS(Indices!$C:$C,Indices!$A:$A,E21,Indices!$B:$B,F21)) | H21: =IF(INDEX(Baux!$P:$P,MATCH($A21,Baux!$A:$A,0))="Base fixe",INDEX(Baux!$N:$N,MATCH($A21,Baux!$A:$A,0)),IF(K20="Geler – rattrapage possible",H20,F20)) | I21: =IF(SUMIFS(Indices!$C:$C,Indices!$A:$A,E21,Indices!$B:$B,H21)=0,"",SUMIFS(Indices!$C:$C,Indices!$A:$A,E21,Indices!$B:$B,H21)) | J21: =IF(OR(G21="",I21=""),"",G21/I21) | L21: =IF(INDEX(Baux!$P:$P,MATCH($A21,Baux!$A:$A,0))="Base fixe",INDEX(Baux!$I:$I,MATCH($A21,Baux!$A:$A,0)),N20) | M21: =IF(OR(J21="",L21=""),"",ROUND(L21*J21,2)) | N21: =IF(LEFT(K21,5)="Geler",O21,IF(M21="","",IF(INDEX(Baux!$Q:$Q,MATCH($A21,Baux!$A:$A,0))="",M21,MIN(M21,ROUND(L21*(1+INDEX(Baux!$Q:$Q,MATCH($A21,Baux!$A:$A,0))/100)^IF(INDEX(Baux!$P:$P,MATCH($A21,Baux!$A:$A,0))="Base fixe",C21*INDEX(Baux!$O:$O,MATCH($A21,Baux!$A:$A,0)),VALUE(LEFT(F21,4))-VALUE(LEFT(H21,4))),2))))) | O21: =N20 | P21: =IF(OR(N21="",O21=""),"",N21/O21-1) | Q21: =IF(N21="","",N21/12) | R21: =IF(N21="","",N21/IF(INDEX(Baux!$L:$L,MATCH($A21,Baux!$A:$A,0))="Mensuelle",12,IF(INDEX(Baux!$L:$L,MATCH($A21,Baux!$A:$A,0))="Trimestrielle",4,IF(INDEX(Baux!$L:$L,MATCH($A21,Baux!$A:$A,0))="Semestrielle",2,1)))) | S21: =IF(INDEX(Baux!$J:$J,MATCH($A21,Baux!$A:$A,0))="",0,INDEX(Baux!$J:$J,MATCH($A21,Baux!$A:$A,0)))/IF(INDEX(Baux!$L:$L,MATCH($A21,Baux!$A:$A,0))="Mensuelle",12,IF(INDEX(Baux!$L:$L,MATCH($A21,Baux!$A:$A,0))="Trimestrielle",4,IF(INDEX(Baux!$L:$L,MATCH($A21,Baux!$A:$A,0))="Semestrielle",2,1))) | T21: =IF(R21="","",(R21+S21)*INDEX(Baux!$K:$K,MATCH($A21,Baux!$A:$A,0))/100) | U21: =IF(R21="","",R21+S21+T21) | V21: =IF(LEFT(K21,5)="Geler","❄ Gelée",IF(G21="",IF(D21<=TODAY(),"⚠ Indice attendu","À venir"),IF(D21<=TODAY(),"✔ Calculable","Indice connu – à venir"))) | AB21: =A21&"#"&C21 | AC21: =IF(AND(D21<=TODAY(),N21<>""),1,0)
A22: B03 | B22: =INDEX(Baux!$B:$B,MATCH($A22,Baux!$A:$A,0)) | C22: 9 | D22: =EDATE(INDEX(Baux!$F:$F,MATCH($A22,Baux!$A:$A,0)),12*INDEX(Baux!$O:$O,MATCH($A22,Baux!$A:$A,0))*C22) | E22: =INDEX(Baux!$M:$M,MATCH($A22,Baux!$A:$A,0)) | F22: =TEXT(VALUE(LEFT(INDEX(Baux!$N:$N,MATCH($A22,Baux!$A:$A,0)),4))+C22*INDEX(Baux!$O:$O,MATCH($A22,Baux!$A:$A,0)),"0")&RIGHT(INDEX(Baux!$N:$N,MATCH($A22,Baux!$A:$A,0)),3) | G22: =IF(SUMIFS(Indices!$C:$C,Indices!$A:$A,E22,Indices!$B:$B,F22)=0,"",SUMIFS(Indices!$C:$C,Indices!$A:$A,E22,Indices!$B:$B,F22)) | H22: =IF(INDEX(Baux!$P:$P,MATCH($A22,Baux!$A:$A,0))="Base fixe",INDEX(Baux!$N:$N,MATCH($A22,Baux!$A:$A,0)),IF(K21="Geler – rattrapage possible",H21,F21)) | I22: =IF(SUMIFS(Indices!$C:$C,Indices!$A:$A,E22,Indices!$B:$B,H22)=0,"",SUMIFS(Indices!$C:$C,Indices!$A:$A,E22,Indices!$B:$B,H22)) | J22: =IF(OR(G22="",I22=""),"",G22/I22) | L22: =IF(INDEX(Baux!$P:$P,MATCH($A22,Baux!$A:$A,0))="Base fixe",INDEX(Baux!$I:$I,MATCH($A22,Baux!$A:$A,0)),N21) | M22: =IF(OR(J22="",L22=""),"",ROUND(L22*J22,2)) | N22: =IF(LEFT(K22,5)="Geler",O22,IF(M22="","",IF(INDEX(Baux!$Q:$Q,MATCH($A22,Baux!$A:$A,0))="",M22,MIN(M22,ROUND(L22*(1+INDEX(Baux!$Q:$Q,MATCH($A22,Baux!$A:$A,0))/100)^IF(INDEX(Baux!$P:$P,MATCH($A22,Baux!$A:$A,0))="Base fixe",C22*INDEX(Baux!$O:$O,MATCH($A22,Baux!$A:$A,0)),VALUE(LEFT(F22,4))-VALUE(LEFT(H22,4))),2))))) | O22: =N21 | P22: =IF(OR(N22="",O22=""),"",N22/O22-1) | Q22: =IF(N22="","",N22/12) | R22: =IF(N22="","",N22/IF(INDEX(Baux!$L:$L,MATCH($A22,Baux!$A:$A,0))="Mensuelle",12,IF(INDEX(Baux!$L:$L,MATCH($A22,Baux!$A:$A,0))="Trimestrielle",4,IF(INDEX(Baux!$L:$L,MATCH($A22,Baux!$A:$A,0))="Semestrielle",2,1)))) | S22: =IF(INDEX(Baux!$J:$J,MATCH($A22,Baux!$A:$A,0))="",0,INDEX(Baux!$J:$J,MATCH($A22,Baux!$A:$A,0)))/IF(INDEX(Baux!$L:$L,MATCH($A22,Baux!$A:$A,0))="Mensuelle",12,IF(INDEX(Baux!$L:$L,MATCH($A22,Baux!$A:$A,0))="Trimestrielle",4,IF(INDEX(Baux!$L:$L,MATCH($A22,Baux!$A:$A,0))="Semestrielle",2,1))) | T22: =IF(R22="","",(R22+S22)*INDEX(Baux!$K:$K,MATCH($A22,Baux!$A:$A,0))/100) | U22: =IF(R22="","",R22+S22+T22) | V22: =IF(LEFT(K22,5)="Geler","❄ Gelée",IF(G22="",IF(D22<=TODAY(),"⚠ Indice attendu","À venir"),IF(D22<=TODAY(),"✔ Calculable","Indice connu – à venir"))) | AB22: =A22&"#"&C22 | AC22: =IF(AND(D22<=TODAY(),N22<>""),1,0)
A23: B04 | B23: =INDEX(Baux!$B:$B,MATCH($A23,Baux!$A:$A,0)) | C23: 1 | D23: =EDATE(INDEX(Baux!$F:$F,MATCH($A23,Baux!$A:$A,0)),12*INDEX(Baux!$O:$O,MATCH($A23,Baux!$A:$A,0))*C23) | E23: =INDEX(Baux!$M:$M,MATCH($A23,Baux!$A:$A,0)) | F23: =TEXT(VALUE(LEFT(INDEX(Baux!$N:$N,MATCH($A23,Baux!$A:$A,0)),4))+C23*INDEX(Baux!$O:$O,MATCH($A23,Baux!$A:$A,0)),"0")&RIGHT(INDEX(Baux!$N:$N,MATCH($A23,Baux!$A:$A,0)),3) | G23: =IF(SUMIFS(Indices!$C:$C,Indices!$A:$A,E23,Indices!$B:$B,F23)=0,"",SUMIFS(Indices!$C:$C,Indices!$A:$A,E23,Indices!$B:$B,F23)) | H23: =INDEX(Baux!$N:$N,MATCH($A23,Baux!$A:$A,0)) | I23: =IF(SUMIFS(Indices!$C:$C,Indices!$A:$A,E23,Indices!$B:$B,H23)=0,"",SUMIFS(Indices!$C:$C,Indices!$A:$A,E23,Indices!$B:$B,H23)) | J23: =IF(OR(G23="",I23=""),"",G23/I23) | L23: =INDEX(Baux!$I:$I,MATCH($A23,Baux!$A:$A,0)) | M23: =IF(OR(J23="",L23=""),"",ROUND(L23*J23,2)) | N23: =IF(LEFT(K23,5)="Geler",O23,IF(M23="","",IF(INDEX(Baux!$Q:$Q,MATCH($A23,Baux!$A:$A,0))="",M23,MIN(M23,ROUND(L23*(1+INDEX(Baux!$Q:$Q,MATCH($A23,Baux!$A:$A,0))/100)^IF(INDEX(Baux!$P:$P,MATCH($A23,Baux!$A:$A,0))="Base fixe",C23*INDEX(Baux!$O:$O,MATCH($A23,Baux!$A:$A,0)),VALUE(LEFT(F23,4))-VALUE(LEFT(H23,4))),2))))) | O23: =INDEX(Baux!$I:$I,MATCH($A23,Baux!$A:$A,0)) | P23: =IF(OR(N23="",O23=""),"",N23/O23-1) | Q23: =IF(N23="","",N23/12) | R23: =IF(N23="","",N23/IF(INDEX(Baux!$L:$L,MATCH($A23,Baux!$A:$A,0))="Mensuelle",12,IF(INDEX(Baux!$L:$L,MATCH($A23,Baux!$A:$A,0))="Trimestrielle",4,IF(INDEX(Baux!$L:$L,MATCH($A23,Baux!$A:$A,0))="Semestrielle",2,1)))) | S23: =IF(INDEX(Baux!$J:$J,MATCH($A23,Baux!$A:$A,0))="",0,INDEX(Baux!$J:$J,MATCH($A23,Baux!$A:$A,0)))/IF(INDEX(Baux!$L:$L,MATCH($A23,Baux!$A:$A,0))="Mensuelle",12,IF(INDEX(Baux!$L:$L,MATCH($A23,Baux!$A:$A,0))="Trimestrielle",4,IF(INDEX(Baux!$L:$L,MATCH($A23,Baux!$A:$A,0))="Semestrielle",2,1))) | T23: =IF(R23="","",(R23+S23)*INDEX(Baux!$K:$K,MATCH($A23,Baux!$A:$A,0))/100) | U23: =IF(R23="","",R23+S23+T23) | V23: =IF(LEFT(K23,5)="Geler","❄ Gelée",IF(G23="",IF(D23<=TODAY(),"⚠ Indice attendu","À venir"),IF(D23<=TODAY(),"✔ Calculable","Indice connu – à venir"))) | AB23: =A23&"#"&C23 | AC23: =IF(AND(D23<=TODAY(),N23<>""),1,0)
A24: B04 | B24: =INDEX(Baux!$B:$B,MATCH($A24,Baux!$A:$A,0)) | C24: 2 | D24: =EDATE(INDEX(Baux!$F:$F,MATCH($A24,Baux!$A:$A,0)),12*INDEX(Baux!$O:$O,MATCH($A24,Baux!$A:$A,0))*C24) | E24: =INDEX(Baux!$M:$M,MATCH($A24,Baux!$A:$A,0)) | F24: =TEXT(VALUE(LEFT(INDEX(Baux!$N:$N,MATCH($A24,Baux!$A:$A,0)),4))+C24*INDEX(Baux!$O:$O,MATCH($A24,Baux!$A:$A,0)),"0")&RIGHT(INDEX(Baux!$N:$N,MATCH($A24,Baux!$A:$A,0)),3) | G24: =IF(SUMIFS(Indices!$C:$C,Indices!$A:$A,E24,Indices!$B:$B,F24)=0,"",SUMIFS(Indices!$C:$C,Indices!$A:$A,E24,Indices!$B:$B,F24)) | H24: =IF(INDEX(Baux!$P:$P,MATCH($A24,Baux!$A:$A,0))="Base fixe",INDEX(Baux!$N:$N,MATCH($A24,Baux!$A:$A,0)),IF(K23="Geler – rattrapage possible",H23,F23)) | I24: =IF(SUMIFS(Indices!$C:$C,Indices!$A:$A,E24,Indices!$B:$B,H24)=0,"",SUMIFS(Indices!$C:$C,Indices!$A:$A,E24,Indices!$B:$B,H24)) | J24: =IF(OR(G24="",I24=""),"",G24/I24) | L24: =IF(INDEX(Baux!$P:$P,MATCH($A24,Baux!$A:$A,0))="Base fixe",INDEX(Baux!$I:$I,MATCH($A24,Baux!$A:$A,0)),N23) | M24: =IF(OR(J24="",L24=""),"",ROUND(L24*J24,2)) | N24: =IF(LEFT(K24,5)="Geler",O24,IF(M24="","",IF(INDEX(Baux!$Q:$Q,MATCH($A24,Baux!$A:$A,0))="",M24,MIN(M24,ROUND(L24*(1+INDEX(Baux!$Q:$Q,MATCH($A24,Baux!$A:$A,0))/100)^IF(INDEX(Baux!$P:$P,MATCH($A24,Baux!$A:$A,0))="Base fixe",C24*INDEX(Baux!$O:$O,MATCH($A24,Baux!$A:$A,0)),VALUE(LEFT(F24,4))-VALUE(LEFT(H24,4))),2))))) | O24: =N23 | P24: =IF(OR(N24="",O24=""),"",N24/O24-1) | Q24: =IF(N24="","",N24/12) | R24: =IF(N24="","",N24/IF(INDEX(Baux!$L:$L,MATCH($A24,Baux!$A:$A,0))="Mensuelle",12,IF(INDEX(Baux!$L:$L,MATCH($A24,Baux!$A:$A,0))="Trimestrielle",4,IF(INDEX(Baux!$L:$L,MATCH($A24,Baux!$A:$A,0))="Semestrielle",2,1)))) | S24: =IF(INDEX(Baux!$J:$J,MATCH($A24,Baux!$A:$A,0))="",0,INDEX(Baux!$J:$J,MATCH($A24,Baux!$A:$A,0)))/IF(INDEX(Baux!$L:$L,MATCH($A24,Baux!$A:$A,0))="Mensuelle",12,IF(INDEX(Baux!$L:$L,MATCH($A24,Baux!$A:$A,0))="Trimestrielle",4,IF(INDEX(Baux!$L:$L,MATCH($A24,Baux!$A:$A,0))="Semestrielle",2,1))) | T24: =IF(R24="","",(R24+S24)*INDEX(Baux!$K:$K,MATCH($A24,Baux!$A:$A,0))/100) | U24: =IF(R24="","",R24+S24+T24) | V24: =IF(LEFT(K24,5)="Geler","❄ Gelée",IF(G24="",IF(D24<=TODAY(),"⚠ Indice attendu","À venir"),IF(D24<=TODAY(),"✔ Calculable","Indice connu – à venir"))) | AB24: =A24&"#"&C24 | AC24: =IF(AND(D24<=TODAY(),N24<>""),1,0)
A25: B04 | B25: =INDEX(Baux!$B:$B,MATCH($A25,Baux!$A:$A,0)) | C25: 3 | D25: =EDATE(INDEX(Baux!$F:$F,MATCH($A25,Baux!$A:$A,0)),12*INDEX(Baux!$O:$O,MATCH($A25,Baux!$A:$A,0))*C25) | E25: =INDEX(Baux!$M:$M,MATCH($A25,Baux!$A:$A,0)) | F25: =TEXT(VALUE(LEFT(INDEX(Baux!$N:$N,MATCH($A25,Baux!$A:$A,0)),4))+C25*INDEX(Baux!$O:$O,MATCH($A25,Baux!$A:$A,0)),"0")&RIGHT(INDEX(Baux!$N:$N,MATCH($A25,Baux!$A:$A,0)),3) | G25: =IF(SUMIFS(Indices!$C:$C,Indices!$A:$A,E25,Indices!$B:$B,F25)=0,"",SUMIFS(Indices!$C:$C,Indices!$A:$A,E25,Indices!$B:$B,F25)) | H25: =IF(INDEX(Baux!$P:$P,MATCH($A25,Baux!$A:$A,0))="Base fixe",INDEX(Baux!$N:$N,MATCH($A25,Baux!$A:$A,0)),IF(K24="Geler – rattrapage possible",H24,F24)) | I25: =IF(SUMIFS(Indices!$C:$C,Indices!$A:$A,E25,Indices!$B:$B,H25)=0,"",SUMIFS(Indices!$C:$C,Indices!$A:$A,E25,Indices!$B:$B,H25)) | J25: =IF(OR(G25="",I25=""),"",G25/I25) | L25: =IF(INDEX(Baux!$P:$P,MATCH($A25,Baux!$A:$A,0))="Base fixe",INDEX(Baux!$I:$I,MATCH($A25,Baux!$A:$A,0)),N24) | M25: =IF(OR(J25="",L25=""),"",ROUND(L25*J25,2)) | N25: =IF(LEFT(K25,5)="Geler",O25,IF(M25="","",IF(INDEX(Baux!$Q:$Q,MATCH($A25,Baux!$A:$A,0))="",M25,MIN(M25,ROUND(L25*(1+INDEX(Baux!$Q:$Q,MATCH($A25,Baux!$A:$A,0))/100)^IF(INDEX(Baux!$P:$P,MATCH($A25,Baux!$A:$A,0))="Base fixe",C25*INDEX(Baux!$O:$O,MATCH($A25,Baux!$A:$A,0)),VALUE(LEFT(F25,4))-VALUE(LEFT(H25,4))),2))))) | O25: =N24 | P25: =IF(OR(N25="",O25=""),"",N25/O25-1) | Q25: =IF(N25="","",N25/12) | R25: =IF(N25="","",N25/IF(INDEX(Baux!$L:$L,MATCH($A25,Baux!$A:$A,0))="Mensuelle",12,IF(INDEX(Baux!$L:$L,MATCH($A25,Baux!$A:$A,0))="Trimestrielle",4,IF(INDEX(Baux!$L:$L,MATCH($A25,Baux!$A:$A,0))="Semestrielle",2,1)))) | S25: =IF(INDEX(Baux!$J:$J,MATCH($A25,Baux!$A:$A,0))="",0,INDEX(Baux!$J:$J,MATCH($A25,Baux!$A:$A,0)))/IF(INDEX(Baux!$L:$L,MATCH($A25,Baux!$A:$A,0))="Mensuelle",12,IF(INDEX(Baux!$L:$L,MATCH($A25,Baux!$A:$A,0))="Trimestrielle",4,IF(INDEX(Baux!$L:$L,MATCH($A25,Baux!$A:$A,0))="Semestrielle",2,1))) | T25: =IF(R25="","",(R25+S25)*INDEX(Baux!$K:$K,MATCH($A25,Baux!$A:$A,0))/100) | U25: =IF(R25="","",R25+S25+T25) | V25: =IF(LEFT(K25,5)="Geler","❄ Gelée",IF(G25="",IF(D25<=TODAY(),"⚠ Indice attendu","À venir"),IF(D25<=TODAY(),"✔ Calculable","Indice connu – à venir"))) | AB25: =A25&"#"&C25 | AC25: =IF(AND(D25<=TODAY(),N25<>""),1,0)
A26: B04 | B26: =INDEX(Baux!$B:$B,MATCH($A26,Baux!$A:$A,0)) | C26: 4 | D26: =EDATE(INDEX(Baux!$F:$F,MATCH($A26,Baux!$A:$A,0)),12*INDEX(Baux!$O:$O,MATCH($A26,Baux!$A:$A,0))*C26) | E26: =INDEX(Baux!$M:$M,MATCH($A26,Baux!$A:$A,0)) | F26: =TEXT(VALUE(LEFT(INDEX(Baux!$N:$N,MATCH($A26,Baux!$A:$A,0)),4))+C26*INDEX(Baux!$O:$O,MATCH($A26,Baux!$A:$A,0)),"0")&RIGHT(INDEX(Baux!$N:$N,MATCH($A26,Baux!$A:$A,0)),3) | G26: =IF(SUMIFS(Indices!$C:$C,Indices!$A:$A,E26,Indices!$B:$B,F26)=0,"",SUMIFS(Indices!$C:$C,Indices!$A:$A,E26,Indices!$B:$B,F26)) | H26: =IF(INDEX(Baux!$P:$P,MATCH($A26,Baux!$A:$A,0))="Base fixe",INDEX(Baux!$N:$N,MATCH($A26,Baux!$A:$A,0)),IF(K25="Geler – rattrapage possible",H25,F25)) | I26: =IF(SUMIFS(Indices!$C:$C,Indices!$A:$A,E26,Indices!$B:$B,H26)=0,"",SUMIFS(Indices!$C:$C,Indices!$A:$A,E26,Indices!$B:$B,H26)) | J26: =IF(OR(G26="",I26=""),"",G26/I26) | L26: =IF(INDEX(Baux!$P:$P,MATCH($A26,Baux!$A:$A,0))="Base fixe",INDEX(Baux!$I:$I,MATCH($A26,Baux!$A:$A,0)),N25) | M26: =IF(OR(J26="",L26=""),"",ROUND(L26*J26,2)) | N26: =IF(LEFT(K26,5)="Geler",O26,IF(M26="","",IF(INDEX(Baux!$Q:$Q,MATCH($A26,Baux!$A:$A,0))="",M26,MIN(M26,ROUND(L26*(1+INDEX(Baux!$Q:$Q,MATCH($A26,Baux!$A:$A,0))/100)^IF(INDEX(Baux!$P:$P,MATCH($A26,Baux!$A:$A,0))="Base fixe",C26*INDEX(Baux!$O:$O,MATCH($A26,Baux!$A:$A,0)),VALUE(LEFT(F26,4))-VALUE(LEFT(H26,4))),2))))) | O26: =N25 | P26: =IF(OR(N26="",O26=""),"",N26/O26-1) | Q26: =IF(N26="","",N26/12) | R26: =IF(N26="","",N26/IF(INDEX(Baux!$L:$L,MATCH($A26,Baux!$A:$A,0))="Mensuelle",12,IF(INDEX(Baux!$L:$L,MATCH($A26,Baux!$A:$A,0))="Trimestrielle",4,IF(INDEX(Baux!$L:$L,MATCH($A26,Baux!$A:$A,0))="Semestrielle",2,1)))) | S26: =IF(INDEX(Baux!$J:$J,MATCH($A26,Baux!$A:$A,0))="",0,INDEX(Baux!$J:$J,MATCH($A26,Baux!$A:$A,0)))/IF(INDEX(Baux!$L:$L,MATCH($A26,Baux!$A:$A,0))="Mensuelle",12,IF(INDEX(Baux!$L:$L,MATCH($A26,Baux!$A:$A,0))="Trimestrielle",4,IF(INDEX(Baux!$L:$L,MATCH($A26,Baux!$A:$A,0))="Semestrielle",2,1))) | T26: =IF(R26="","",(R26+S26)*INDEX(Baux!$K:$K,MATCH($A26,Baux!$A:$A,0))/100) | U26: =IF(R26="","",R26+S26+T26) | V26: =IF(LEFT(K26,5)="Geler","❄ Gelée",IF(G26="",IF(D26<=TODAY(),"⚠ Indice attendu","À venir"),IF(D26<=TODAY(),"✔ Calculable","Indice connu – à venir"))) | AB26: =A26&"#"&C26 | AC26: =IF(AND(D26<=TODAY(),N26<>""),1,0)
A27: B04 | B27: =INDEX(Baux!$B:$B,MATCH($A27,Baux!$A:$A,0)) | C27: 5 | D27: =EDATE(INDEX(Baux!$F:$F,MATCH($A27,Baux!$A:$A,0)),12*INDEX(Baux!$O:$O,MATCH($A27,Baux!$A:$A,0))*C27) | E27: =INDEX(Baux!$M:$M,MATCH($A27,Baux!$A:$A,0)) | F27: =TEXT(VALUE(LEFT(INDEX(Baux!$N:$N,MATCH($A27,Baux!$A:$A,0)),4))+C27*INDEX(Baux!$O:$O,MATCH($A27,Baux!$A:$A,0)),"0")&RIGHT(INDEX(Baux!$N:$N,MATCH($A27,Baux!$A:$A,0)),3) | G27: =IF(SUMIFS(Indices!$C:$C,Indices!$A:$A,E27,Indices!$B:$B,F27)=0,"",SUMIFS(Indices!$C:$C,Indices!$A:$A,E27,Indices!$B:$B,F27)) | H27: =IF(INDEX(Baux!$P:$P,MATCH($A27,Baux!$A:$A,0))="Base fixe",INDEX(Baux!$N:$N,MATCH($A27,Baux!$A:$A,0)),IF(K26="Geler – rattrapage possible",H26,F26)) | I27: =IF(SUMIFS(Indices!$C:$C,Indices!$A:$A,E27,Indices!$B:$B,H27)=0,"",SUMIFS(Indices!$C:$C,Indices!$A:$A,E27,Indices!$B:$B,H27)) | J27: =IF(OR(G27="",I27=""),"",G27/I27) | L27: =IF(INDEX(Baux!$P:$P,MATCH($A27,Baux!$A:$A,0))="Base fixe",INDEX(Baux!$I:$I,MATCH($A27,Baux!$A:$A,0)),N26) | M27: =IF(OR(J27="",L27=""),"",ROUND(L27*J27,2)) | N27: =IF(LEFT(K27,5)="Geler",O27,IF(M27="","",IF(INDEX(Baux!$Q:$Q,MATCH($A27,Baux!$A:$A,0))="",M27,MIN(M27,ROUND(L27*(1+INDEX(Baux!$Q:$Q,MATCH($A27,Baux!$A:$A,0))/100)^IF(INDEX(Baux!$P:$P,MATCH($A27,Baux!$A:$A,0))="Base fixe",C27*INDEX(Baux!$O:$O,MATCH($A27,Baux!$A:$A,0)),VALUE(LEFT(F27,4))-VALUE(LEFT(H27,4))),2))))) | O27: =N26 | P27: =IF(OR(N27="",O27=""),"",N27/O27-1) | Q27: =IF(N27="","",N27/12) | R27: =IF(N27="","",N27/IF(INDEX(Baux!$L:$L,MATCH($A27,Baux!$A:$A,0))="Mensuelle",12,IF(INDEX(Baux!$L:$L,MATCH($A27,Baux!$A:$A,0))="Trimestrielle",4,IF(INDEX(Baux!$L:$L,MATCH($A27,Baux!$A:$A,0))="Semestrielle",2,1)))) | S27: =IF(INDEX(Baux!$J:$J,MATCH($A27,Baux!$A:$A,0))="",0,INDEX(Baux!$J:$J,MATCH($A27,Baux!$A:$A,0)))/IF(INDEX(Baux!$L:$L,MATCH($A27,Baux!$A:$A,0))="Mensuelle",12,IF(INDEX(Baux!$L:$L,MATCH($A27,Baux!$A:$A,0))="Trimestrielle",4,IF(INDEX(Baux!$L:$L,MATCH($A27,Baux!$A:$A,0))="Semestrielle",2,1))) | T27: =IF(R27="","",(R27+S27)*INDEX(Baux!$K:$K,MATCH($A27,Baux!$A:$A,0))/100) | U27: =IF(R27="","",R27+S27+T27) | V27: =IF(LEFT(K27,5)="Geler","❄ Gelée",IF(G27="",IF(D27<=TODAY(),"⚠ Indice attendu","À venir"),IF(D27<=TODAY(),"✔ Calculable","Indice connu – à venir"))) | AB27: =A27&"#"&C27 | AC27: =IF(AND(D27<=TODAY(),N27<>""),1,0)
A28: B04 | B28: =INDEX(Baux!$B:$B,MATCH($A28,Baux!$A:$A,0)) | C28: 6 | D28: =EDATE(INDEX(Baux!$F:$F,MATCH($A28,Baux!$A:$A,0)),12*INDEX(Baux!$O:$O,MATCH($A28,Baux!$A:$A,0))*C28) | E28: =INDEX(Baux!$M:$M,MATCH($A28,Baux!$A:$A,0)) | F28: =TEXT(VALUE(LEFT(INDEX(Baux!$N:$N,MATCH($A28,Baux!$A:$A,0)),4))+C28*INDEX(Baux!$O:$O,MATCH($A28,Baux!$A:$A,0)),"0")&RIGHT(INDEX(Baux!$N:$N,MATCH($A28,Baux!$A:$A,0)),3) | G28: =IF(SUMIFS(Indices!$C:$C,Indices!$A:$A,E28,Indices!$B:$B,F28)=0,"",SUMIFS(Indices!$C:$C,Indices!$A:$A,E28,Indices!$B:$B,F28)) | H28: =IF(INDEX(Baux!$P:$P,MATCH($A28,Baux!$A:$A,0))="Base fixe",INDEX(Baux!$N:$N,MATCH($A28,Baux!$A:$A,0)),IF(K27="Geler – rattrapage possible",H27,F27)) | I28: =IF(SUMIFS(Indices!$C:$C,Indices!$A:$A,E28,Indices!$B:$B,H28)=0,"",SUMIFS(Indices!$C:$C,Indices!$A:$A,E28,Indices!$B:$B,H28)) | J28: =IF(OR(G28="",I28=""),"",G28/I28) | L28: =IF(INDEX(Baux!$P:$P,MATCH($A28,Baux!$A:$A,0))="Base fixe",INDEX(Baux!$I:$I,MATCH($A28,Baux!$A:$A,0)),N27) | M28: =IF(OR(J28="",L28=""),"",ROUND(L28*J28,2)) | N28: =IF(LEFT(K28,5)="Geler",O28,IF(M28="","",IF(INDEX(Baux!$Q:$Q,MATCH($A28,Baux!$A:$A,0))="",M28,MIN(M28,ROUND(L28*(1+INDEX(Baux!$Q:$Q,MATCH($A28,Baux!$A:$A,0))/100)^IF(INDEX(Baux!$P:$P,MATCH($A28,Baux!$A:$A,0))="Base fixe",C28*INDEX(Baux!$O:$O,MATCH($A28,Baux!$A:$A,0)),VALUE(LEFT(F28,4))-VALUE(LEFT(H28,4))),2))))) | O28: =N27 | P28: =IF(OR(N28="",O28=""),"",N28/O28-1) | Q28: =IF(N28="","",N28/12) | R28: =IF(N28="","",N28/IF(INDEX(Baux!$L:$L,MATCH($A28,Baux!$A:$A,0))="Mensuelle",12,IF(INDEX(Baux!$L:$L,MATCH($A28,Baux!$A:$A,0))="Trimestrielle",4,IF(INDEX(Baux!$L:$L,MATCH($A28,Baux!$A:$A,0))="Semestrielle",2,1)))) | S28: =IF(INDEX(Baux!$J:$J,MATCH($A28,Baux!$A:$A,0))="",0,INDEX(Baux!$J:$J,MATCH($A28,Baux!$A:$A,0)))/IF(INDEX(Baux!$L:$L,MATCH($A28,Baux!$A:$A,0))="Mensuelle",12,IF(INDEX(Baux!$L:$L,MATCH($A28,Baux!$A:$A,0))="Trimestrielle",4,IF(INDEX(Baux!$L:$L,MATCH($A28,Baux!$A:$A,0))="Semestrielle",2,1))) | T28: =IF(R28="","",(R28+S28)*INDEX(Baux!$K:$K,MATCH($A28,Baux!$A:$A,0))/100) | U28: =IF(R28="","",R28+S28+T28) | V28: =IF(LEFT(K28,5)="Geler","❄ Gelée",IF(G28="",IF(D28<=TODAY(),"⚠ Indice attendu","À venir"),IF(D28<=TODAY(),"✔ Calculable","Indice connu – à venir"))) | AB28: =A28&"#"&C28 | AC28: =IF(AND(D28<=TODAY(),N28<>""),1,0)
A29: B04 | B29: =INDEX(Baux!$B:$B,MATCH($A29,Baux!$A:$A,0)) | C29: 7 | D29: =EDATE(INDEX(Baux!$F:$F,MATCH($A29,Baux!$A:$A,0)),12*INDEX(Baux!$O:$O,MATCH($A29,Baux!$A:$A,0))*C29) | E29: =INDEX(Baux!$M:$M,MATCH($A29,Baux!$A:$A,0)) | F29: =TEXT(VALUE(LEFT(INDEX(Baux!$N:$N,MATCH($A29,Baux!$A:$A,0)),4))+C29*INDEX(Baux!$O:$O,MATCH($A29,Baux!$A:$A,0)),"0")&RIGHT(INDEX(Baux!$N:$N,MATCH($A29,Baux!$A:$A,0)),3) | G29: =IF(SUMIFS(Indices!$C:$C,Indices!$A:$A,E29,Indices!$B:$B,F29)=0,"",SUMIFS(Indices!$C:$C,Indices!$A:$A,E29,Indices!$B:$B,F29)) | H29: =IF(INDEX(Baux!$P:$P,MATCH($A29,Baux!$A:$A,0))="Base fixe",INDEX(Baux!$N:$N,MATCH($A29,Baux!$A:$A,0)),IF(K28="Geler – rattrapage possible",H28,F28)) | I29: =IF(SUMIFS(Indices!$C:$C,Indices!$A:$A,E29,Indices!$B:$B,H29)=0,"",SUMIFS(Indices!$C:$C,Indices!$A:$A,E29,Indices!$B:$B,H29)) | J29: =IF(OR(G29="",I29=""),"",G29/I29) | L29: =IF(INDEX(Baux!$P:$P,MATCH($A29,Baux!$A:$A,0))="Base fixe",INDEX(Baux!$I:$I,MATCH($A29,Baux!$A:$A,0)),N28) | M29: =IF(OR(J29="",L29=""),"",ROUND(L29*J29,2)) | N29: =IF(LEFT(K29,5)="Geler",O29,IF(M29="","",IF(INDEX(Baux!$Q:$Q,MATCH($A29,Baux!$A:$A,0))="",M29,MIN(M29,ROUND(L29*(1+INDEX(Baux!$Q:$Q,MATCH($A29,Baux!$A:$A,0))/100)^IF(INDEX(Baux!$P:$P,MATCH($A29,Baux!$A:$A,0))="Base fixe",C29*INDEX(Baux!$O:$O,MATCH($A29,Baux!$A:$A,0)),VALUE(LEFT(F29,4))-VALUE(LEFT(H29,4))),2))))) | O29: =N28 | P29: =IF(OR(N29="",O29=""),"",N29/O29-1) | Q29: =IF(N29="","",N29/12) | R29: =IF(N29="","",N29/IF(INDEX(Baux!$L:$L,MATCH($A29,Baux!$A:$A,0))="Mensuelle",12,IF(INDEX(Baux!$L:$L,MATCH($A29,Baux!$A:$A,0))="Trimestrielle",4,IF(INDEX(Baux!$L:$L,MATCH($A29,Baux!$A:$A,0))="Semestrielle",2,1)))) | S29: =IF(INDEX(Baux!$J:$J,MATCH($A29,Baux!$A:$A,0))="",0,INDEX(Baux!$J:$J,MATCH($A29,Baux!$A:$A,0)))/IF(INDEX(Baux!$L:$L,MATCH($A29,Baux!$A:$A,0))="Mensuelle",12,IF(INDEX(Baux!$L:$L,MATCH($A29,Baux!$A:$A,0))="Trimestrielle",4,IF(INDEX(Baux!$L:$L,MATCH($A29,Baux!$A:$A,0))="Semestrielle",2,1))) | T29: =IF(R29="","",(R29+S29)*INDEX(Baux!$K:$K,MATCH($A29,Baux!$A:$A,0))/100) | U29: =IF(R29="","",R29+S29+T29) | V29: =IF(LEFT(K29,5)="Geler","❄ Gelée",IF(G29="",IF(D29<=TODAY(),"⚠ Indice attendu","À venir"),IF(D29<=TODAY(),"✔ Calculable","Indice connu – à venir"))) | AB29: =A29&"#"&C29 | AC29: =IF(AND(D29<=TODAY(),N29<>""),1,0)
A30: B04 | B30: =INDEX(Baux!$B:$B,MATCH($A30,Baux!$A:$A,0)) | C30: 8 | D30: =EDATE(INDEX(Baux!$F:$F,MATCH($A30,Baux!$A:$A,0)),12*INDEX(Baux!$O:$O,MATCH($A30,Baux!$A:$A,0))*C30) | E30: =INDEX(Baux!$M:$M,MATCH($A30,Baux!$A:$A,0)) | F30: =TEXT(VALUE(LEFT(INDEX(Baux!$N:$N,MATCH($A30,Baux!$A:$A,0)),4))+C30*INDEX(Baux!$O:$O,MATCH($A30,Baux!$A:$A,0)),"0")&RIGHT(INDEX(Baux!$N:$N,MATCH($A30,Baux!$A:$A,0)),3) | G30: =IF(SUMIFS(Indices!$C:$C,Indices!$A:$A,E30,Indices!$B:$B,F30)=0,"",SUMIFS(Indices!$C:$C,Indices!$A:$A,E30,Indices!$B:$B,F30)) | H30: =IF(INDEX(Baux!$P:$P,MATCH($A30,Baux!$A:$A,0))="Base fixe",INDEX(Baux!$N:$N,MATCH($A30,Baux!$A:$A,0)),IF(K29="Geler – rattrapage possible",H29,F29)) | I30: =IF(SUMIFS(Indices!$C:$C,Indices!$A:$A,E30,Indices!$B:$B,H30)=0,"",SUMIFS(Indices!$C:$C,Indices!$A:$A,E30,Indices!$B:$B,H30)) | J30: =IF(OR(G30="",I30=""),"",G30/I30) | L30: =IF(INDEX(Baux!$P:$P,MATCH($A30,Baux!$A:$A,0))="Base fixe",INDEX(Baux!$I:$I,MATCH($A30,Baux!$A:$A,0)),N29) | M30: =IF(OR(J30="",L30=""),"",ROUND(L30*J30,2)) | N30: =IF(LEFT(K30,5)="Geler",O30,IF(M30="","",IF(INDEX(Baux!$Q:$Q,MATCH($A30,Baux!$A:$A,0))="",M30,MIN(M30,ROUND(L30*(1+INDEX(Baux!$Q:$Q,MATCH($A30,Baux!$A:$A,0))/100)^IF(INDEX(Baux!$P:$P,MATCH($A30,Baux!$A:$A,0))="Base fixe",C30*INDEX(Baux!$O:$O,MATCH($A30,Baux!$A:$A,0)),VALUE(LEFT(F30,4))-VALUE(LEFT(H30,4))),2))))) | O30: =N29 | P30: =IF(OR(N30="",O30=""),"",N30/O30-1) | Q30: =IF(N30="","",N30/12) | R30: =IF(N30="","",N30/IF(INDEX(Baux!$L:$L,MATCH($A30,Baux!$A:$A,0))="Mensuelle",12,IF(INDEX(Baux!$L:$L,MATCH($A30,Baux!$A:$A,0))="Trimestrielle",4,IF(INDEX(Baux!$L:$L,MATCH($A30,Baux!$A:$A,0))="Semestrielle",2,1)))) | S30: =IF(INDEX(Baux!$J:$J,MATCH($A30,Baux!$A:$A,0))="",0,INDEX(Baux!$J:$J,MATCH($A30,Baux!$A:$A,0)))/IF(INDEX(Baux!$L:$L,MATCH($A30,Baux!$A:$A,0))="Mensuelle",12,IF(INDEX(Baux!$L:$L,MATCH($A30,Baux!$A:$A,0))="Trimestrielle",4,IF(INDEX(Baux!$L:$L,MATCH($A30,Baux!$A:$A,0))="Semestrielle",2,1))) | T30: =IF(R30="","",(R30+S30)*INDEX(Baux!$K:$K,MATCH($A30,Baux!$A:$A,0))/100) | U30: =IF(R30="","",R30+S30+T30) | V30: =IF(LEFT(K30,5)="Geler","❄ Gelée",IF(G30="",IF(D30<=TODAY(),"⚠ Indice attendu","À venir"),IF(D30<=TODAY(),"✔ Calculable","Indice connu – à venir"))) | AB30: =A30&"#"&C30 | AC30: =IF(AND(D30<=TODAY(),N30<>""),1,0)
A31: B04 | B31: =INDEX(Baux!$B:$B,MATCH($A31,Baux!$A:$A,0)) | C31: 9 | D31: =EDATE(INDEX(Baux!$F:$F,MATCH($A31,Baux!$A:$A,0)),12*INDEX(Baux!$O:$O,MATCH($A31,Baux!$A:$A,0))*C31) | E31: =INDEX(Baux!$M:$M,MATCH($A31,Baux!$A:$A,0)) | F31: =TEXT(VALUE(LEFT(INDEX(Baux!$N:$N,MATCH($A31,Baux!$A:$A,0)),4))+C31*INDEX(Baux!$O:$O,MATCH($A31,Baux!$A:$A,0)),"0")&RIGHT(INDEX(Baux!$N:$N,MATCH($A31,Baux!$A:$A,0)),3) | G31: =IF(SUMIFS(Indices!$C:$C,Indices!$A:$A,E31,Indices!$B:$B,F31)=0,"",SUMIFS(Indices!$C:$C,Indices!$A:$A,E31,Indices!$B:$B,F31)) | H31: =IF(INDEX(Baux!$P:$P,MATCH($A31,Baux!$A:$A,0))="Base fixe",INDEX(Baux!$N:$N,MATCH($A31,Baux!$A:$A,0)),IF(K30="Geler – rattrapage possible",H30,F30)) | I31: =IF(SUMIFS(Indices!$C:$C,Indices!$A:$A,E31,Indices!$B:$B,H31)=0,"",SUMIFS(Indices!$C:$C,Indices!$A:$A,E31,Indices!$B:$B,H31)) | J31: =IF(OR(G31="",I31=""),"",G31/I31) | L31: =IF(INDEX(Baux!$P:$P,MATCH($A31,Baux!$A:$A,0))="Base fixe",INDEX(Baux!$I:$I,MATCH($A31,Baux!$A:$A,0)),N30) | M31: =IF(OR(J31="",L31=""),"",ROUND(L31*J31,2)) | N31: =IF(LEFT(K31,5)="Geler",O31,IF(M31="","",IF(INDEX(Baux!$Q:$Q,MATCH($A31,Baux!$A:$A,0))="",M31,MIN(M31,ROUND(L31*(1+INDEX(Baux!$Q:$Q,MATCH($A31,Baux!$A:$A,0))/100)^IF(INDEX(Baux!$P:$P,MATCH($A31,Baux!$A:$A,0))="Base fixe",C31*INDEX(Baux!$O:$O,MATCH($A31,Baux!$A:$A,0)),VALUE(LEFT(F31,4))-VALUE(LEFT(H31,4))),2))))) | O31: =N30 | P31: =IF(OR(N31="",O31=""),"",N31/O31-1) | Q31: =IF(N31="","",N31/12) | R31: =IF(N31="","",N31/IF(INDEX(Baux!$L:$L,MATCH($A31,Baux!$A:$A,0))="Mensuelle",12,IF(INDEX(Baux!$L:$L,MATCH($A31,Baux!$A:$A,0))="Trimestrielle",4,IF(INDEX(Baux!$L:$L,MATCH($A31,Baux!$A:$A,0))="Semestrielle",2,1)))) | S31: =IF(INDEX(Baux!$J:$J,MATCH($A31,Baux!$A:$A,0))="",0,INDEX(Baux!$J:$J,MATCH($A31,Baux!$A:$A,0)))/IF(INDEX(Baux!$L:$L,MATCH($A31,Baux!$A:$A,0))="Mensuelle",12,IF(INDEX(Baux!$L:$L,MATCH($A31,Baux!$A:$A,0))="Trimestrielle",4,IF(INDEX(Baux!$L:$L,MATCH($A31,Baux!$A:$A,0))="Semestrielle",2,1))) | T31: =IF(R31="","",(R31+S31)*INDEX(Baux!$K:$K,MATCH($A31,Baux!$A:$A,0))/100) | U31: =IF(R31="","",R31+S31+T31) | V31: =IF(LEFT(K31,5)="Geler","❄ Gelée",IF(G31="",IF(D31<=TODAY(),"⚠ Indice attendu","À venir"),IF(D31<=TODAY(),"✔ Calculable","Indice connu – à venir"))) | AB31: =A31&"#"&C31 | AC31: =IF(AND(D31<=TODAY(),N31<>""),1,0)

Sheet Alertes
A1: ID bail | B1: Local | C1: Locataire | D1: Indice | E1: Loyer initial annuel HT | F1: N° dernière révision effective | G1: Loyer actuel (annuel HT) | H1: Loyer actuel mensuel HT | I1: Prochaine révision | J1: Trimestre attendu | K1: Indice publié ? | L1: Révisions calculables non appliquées | M1: Révisions gelées | N1: Action | O1: Consigne prochaine révision
A2: B01 | B2: =INDEX(Baux!$B:$B,MATCH($A2,Baux!$A:$A,0)) | C2: =INDEX(Baux!$C:$C,MATCH($A2,Baux!$A:$A,0)) | D2: =INDEX(Baux!$M:$M,MATCH($A2,Baux!$A:$A,0)) | E2: =INDEX(Baux!$I:$I,MATCH($A2,Baux!$A:$A,0)) | F2: =_xlfn.MAXIFS(Révisions!$C:$C,Révisions!$A:$A,A2,Révisions!$AC:$AC,1) | G2: =IF(F2=0,E2,SUMIFS(Révisions!$N:$N,Révisions!$A:$A,A2,Révisions!$C:$C,F2)) | H2: =G2/12 | I2: =IF(_xlfn.MINIFS(Révisions!$D:$D,Révisions!$A:$A,A2,Révisions!$D:$D,">"&TODAY())=0,"—",_xlfn.MINIFS(Révisions!$D:$D,Révisions!$A:$A,A2,Révisions!$D:$D,">"&TODAY())) | J2: =IFERROR(INDEX(Révisions!$F:$F,MATCH(A2&"#"&(F2+1),Révisions!$AB:$AB,0)),"—") | K2: =IF(J2="—","—",IF(SUMIFS(Indices!$C:$C,Indices!$A:$A,D2,Indices!$B:$B,J2)>0,"Oui","Non")) | L2: =COUNTIFS(Révisions!$A:$A,A2,Révisions!$V:$V,"✔ Calculable",Révisions!$X:$X,"<>Oui") | M2: =COUNTIFS(Révisions!$A:$A,A2,Révisions!$V:$V,"❄ Gelée") | N2: =IF(L2>0,"⚠ Facturer la révision ("&L2&" en attente)",IF(AND(I2<>"—",I2-TODAY()<=60),IF(K2="Oui","Révision dans "&INT(I2-TODAY())&" j – indice publié","Révision dans "&INT(I2-TODAY())&" j – indice non publié"),"RAS")) | O2: =IFERROR(INDEX(Révisions!$W:$W,MATCH(A2&"#"&(F2+1),Révisions!$AB:$AB,0))&"","")
A3: B02 | B3: =INDEX(Baux!$B:$B,MATCH($A3,Baux!$A:$A,0)) | C3: =INDEX(Baux!$C:$C,MATCH($A3,Baux!$A:$A,0)) | D3: =INDEX(Baux!$M:$M,MATCH($A3,Baux!$A:$A,0)) | E3: =INDEX(Baux!$I:$I,MATCH($A3,Baux!$A:$A,0)) | F3: =_xlfn.MAXIFS(Révisions!$C:$C,Révisions!$A:$A,A3,Révisions!$AC:$AC,1) | G3: =IF(F3=0,E3,SUMIFS(Révisions!$N:$N,Révisions!$A:$A,A3,Révisions!$C:$C,F3)) | H3: =G3/12 | I3: =IF(_xlfn.MINIFS(Révisions!$D:$D,Révisions!$A:$A,A3,Révisions!$D:$D,">"&TODAY())=0,"—",_xlfn.MINIFS(Révisions!$D:$D,Révisions!$A:$A,A3,Révisions!$D:$D,">"&TODAY())) | J3: =IFERROR(INDEX(Révisions!$F:$F,MATCH(A3&"#"&(F3+1),Révisions!$AB:$AB,0)),"—") | K3: =IF(J3="—","—",IF(SUMIFS(Indices!$C:$C,Indices!$A:$A,D3,Indices!$B:$B,J3)>0,"Oui","Non")) | L3: =COUNTIFS(Révisions!$A:$A,A3,Révisions!$V:$V,"✔ Calculable",Révisions!$X:$X,"<>Oui") | M3: =COUNTIFS(Révisions!$A:$A,A3,Révisions!$V:$V,"❄ Gelée") | N3: =IF(L3>0,"⚠ Facturer la révision ("&L3&" en attente)",IF(AND(I3<>"—",I3-TODAY()<=60),IF(K3="Oui","Révision dans "&INT(I3-TODAY())&" j – indice publié","Révision dans "&INT(I3-TODAY())&" j – indice non publié"),"RAS")) | O3: =IFERROR(INDEX(Révisions!$W:$W,MATCH(A3&"#"&(F3+1),Révisions!$AB:$AB,0))&"","")
A4: B03 | B4: =INDEX(Baux!$B:$B,MATCH($A4,Baux!$A:$A,0)) | C4: =INDEX(Baux!$C:$C,MATCH($A4,Baux!$A:$A,0)) | D4: =INDEX(Baux!$M:$M,MATCH($A4,Baux!$A:$A,0)) | E4: =INDEX(Baux!$I:$I,MATCH($A4,Baux!$A:$A,0)) | F4: =_xlfn.MAXIFS(Révisions!$C:$C,Révisions!$A:$A,A4,Révisions!$AC:$AC,1) | G4: =IF(F4=0,E4,SUMIFS(Révisions!$N:$N,Révisions!$A:$A,A4,Révisions!$C:$C,F4)) | H4: =G4/12 | I4: =IF(_xlfn.MINIFS(Révisions!$D:$D,Révisions!$A:$A,A4,Révisions!$D:$D,">"&TODAY())=0,"—",_xlfn.MINIFS(Révisions!$D:$D,Révisions!$A:$A,A4,Révisions!$D:$D,">"&TODAY())) | J4: =IFERROR(INDEX(Révisions!$F:$F,MATCH(A4&"#"&(F4+1),Révisions!$AB:$AB,0)),"—") | K4: =IF(J4="—","—",IF(SUMIFS(Indices!$C:$C,Indices!$A:$A,D4,Indices!$B:$B,J4)>0,"Oui","Non")) | L4: =COUNTIFS(Révisions!$A:$A,A4,Révisions!$V:$V,"✔ Calculable",Révisions!$X:$X,"<>Oui") | M4: =COUNTIFS(Révisions!$A:$A,A4,Révisions!$V:$V,"❄ Gelée") | N4: =IF(L4>0,"⚠ Facturer la révision ("&L4&" en attente)",IF(AND(I4<>"—",I4-TODAY()<=60),IF(K4="Oui","Révision dans "&INT(I4-TODAY())&" j – indice publié","Révision dans "&INT(I4-TODAY())&" j – indice non publié"),"RAS")) | O4: =IFERROR(INDEX(Révisions!$W:$W,MATCH(A4&"#"&(F4+1),Révisions!$AB:$AB,0))&"","")
A5: B04 | B5: =INDEX(Baux!$B:$B,MATCH($A5,Baux!$A:$A,0)) | C5: =INDEX(Baux!$C:$C,MATCH($A5,Baux!$A:$A,0)) | D5: =INDEX(Baux!$M:$M,MATCH($A5,Baux!$A:$A,0)) | E5: =INDEX(Baux!$I:$I,MATCH($A5,Baux!$A:$A,0)) | F5: =_xlfn.MAXIFS(Révisions!$C:$C,Révisions!$A:$A,A5,Révisions!$AC:$AC,1) | G5: =IF(F5=0,E5,SUMIFS(Révisions!$N:$N,Révisions!$A:$A,A5,Révisions!$C:$C,F5)) | H5: =G5/12 | I5: =IF(_xlfn.MINIFS(Révisions!$D:$D,Révisions!$A:$A,A5,Révisions!$D:$D,">"&TODAY())=0,"—",_xlfn.MINIFS(Révisions!$D:$D,Révisions!$A:$A,A5,Révisions!$D:$D,">"&TODAY())) | J5: =IFERROR(INDEX(Révisions!$F:$F,MATCH(A5&"#"&(F5+1),Révisions!$AB:$AB,0)),"—") | K5: =IF(J5="—","—",IF(SUMIFS(Indices!$C:$C,Indices!$A:$A,D5,Indices!$B:$B,J5)>0,"Oui","Non")) | L5: =COUNTIFS(Révisions!$A:$A,A5,Révisions!$V:$V,"✔ Calculable",Révisions!$X:$X,"<>Oui") | M5: =COUNTIFS(Révisions!$A:$A,A5,Révisions!$V:$V,"❄ Gelée") | N5: =IF(L5>0,"⚠ Facturer la révision ("&L5&" en attente)",IF(AND(I5<>"—",I5-TODAY()<=60),IF(K5="Oui","Révision dans "&INT(I5-TODAY())&" j – indice publié","Révision dans "&INT(I5-TODAY())&" j – indice non publié"),"RAS")) | O5: =IFERROR(INDEX(Révisions!$W:$W,MATCH(A5&"#"&(F5+1),Révisions!$AB:$AB,0))&"","")

Sheet Pennylane
A1: ID bail | B1: Locataire | C1: customer_id | D1: product_id | E1: Libellé de ligne | F1: Périodicité | G1: recurrence.type | H1: Prix unitaire HT / échéance | I1: Charges HT / échéance | J1: TVA (%) | K1: vat_rate (code Pennylane) | L1: Date de début (1er du mois suivant) | M1: Aperçu du corps JSON (POST /billing_subscriptions)
A2: B01 | B2: =INDEX(Baux!$C:$C,MATCH($A2,Baux!$A:$A,0)) | C2: =IF(INDEX(Baux!$R:$R,MATCH($A2,Baux!$A:$A,0))="","À RENSEIGNER",INDEX(Baux!$R:$R,MATCH($A2,Baux!$A:$A,0))) | D2: =IF(INDEX(Baux!$S:$S,MATCH($A2,Baux!$A:$A,0))="","",INDEX(Baux!$S:$S,MATCH($A2,Baux!$A:$A,0))) | E2: ="Loyer "&INDEX(Baux!$B:$B,MATCH($A2,Baux!$A:$A,0))&" – échéance "&LOWER(F2) | F2: =INDEX(Baux!$L:$L,MATCH($A2,Baux!$A:$A,0)) | G2: =IF(F2="Mensuelle","monthly",IF(F2="Trimestrielle","quarterly",IF(F2="Semestrielle","semiannual","yearly"))) | H2: =ROUND(INDEX(Alertes!$G:$G,MATCH(A2,Alertes!$A:$A,0))/IF(F2="Mensuelle",12,IF(F2="Trimestrielle",4,IF(F2="Semestrielle",2,1))),2) | I2: =ROUND(IF(INDEX(Baux!$J:$J,MATCH($A2,Baux!$A:$A,0))="",0,INDEX(Baux!$J:$J,MATCH($A2,Baux!$A:$A,0)))/IF(F2="Mensuelle",12,IF(F2="Trimestrielle",4,IF(F2="Semestrielle",2,1))),2) | J2: =INDEX(Baux!$K:$K,MATCH($A2,Baux!$A:$A,0)) | K2: =IF(J2=20,"FR_200",IF(J2=10,"FR_100",IF(J2=5.5,"FR_55",IF(J2=2.1,"FR_21","exempt")))) | L2: =DATE(YEAR(TODAY()),MONTH(TODAY())+1,1) | M2: ="{""customer_id"": "&C2&", ""start"": """&YEAR(L2)&"-"&TEXT(MONTH(L2),"00")&"-"&TEXT(DAY(L2),"00")&""", ""currency"": ""EUR"", ""recurrence"": {""type"": """&G2&""", ""day_of_month"": 1}, ""invoice_lines"": [{""label"": """&E2&""", ""quantity"": 1, ""raw_currency_unit_price"": "&SUBSTITUTE(TEXT(H2,"0.00"),",",".")&", ""vat_rate"": """&K2&""""&IF(D2<>"",", ""product_id"": "&D2,"")&"}"&IF(I2>0,", {""label"": ""Provision sur charges"", ""quantity"": 1, ""raw_currency_unit_price"": "&SUBSTITUTE(TEXT(I2,"0.00"),",",".")&", ""vat_rate"": """&K2&"""}","")&"]}"
A3: B02 | B3: =INDEX(Baux!$C:$C,MATCH($A3,Baux!$A:$A,0)) | C3: =IF(INDEX(Baux!$R:$R,MATCH($A3,Baux!$A:$A,0))="","À RENSEIGNER",INDEX(Baux!$R:$R,MATCH($A3,Baux!$A:$A,0))) | D3: =IF(INDEX(Baux!$S:$S,MATCH($A3,Baux!$A:$A,0))="","",INDEX(Baux!$S:$S,MATCH($A3,Baux!$A:$A,0))) | E3: ="Loyer "&INDEX(Baux!$B:$B,MATCH($A3,Baux!$A:$A,0))&" – échéance "&LOWER(F3) | F3: =INDEX(Baux!$L:$L,MATCH($A3,Baux!$A:$A,0)) | G3: =IF(F3="Mensuelle","monthly",IF(F3="Trimestrielle","quarterly",IF(F3="Semestrielle","semiannual","yearly"))) | H3: =ROUND(INDEX(Alertes!$G:$G,MATCH(A3,Alertes!$A:$A,0))/IF(F3="Mensuelle",12,IF(F3="Trimestrielle",4,IF(F3="Semestrielle",2,1))),2) | I3: =ROUND(IF(INDEX(Baux!$J:$J,MATCH($A3,Baux!$A:$A,0))="",0,INDEX(Baux!$J:$J,MATCH($A3,Baux!$A:$A,0)))/IF(F3="Mensuelle",12,IF(F3="Trimestrielle",4,IF(F3="Semestrielle",2,1))),2) | J3: =INDEX(Baux!$K:$K,MATCH($A3,Baux!$A:$A,0)) | K3: =IF(J3=20,"FR_200",IF(J3=10,"FR_100",IF(J3=5.5,"FR_55",IF(J3=2.1,"FR_21","exempt")))) | L3: =DATE(YEAR(TODAY()),MONTH(TODAY())+1,1) | M3: ="{""customer_id"": "&C3&", ""start"": """&YEAR(L3)&"-"&TEXT(MONTH(L3),"00")&"-"&TEXT(DAY(L3),"00")&""", ""currency"": ""EUR"", ""recurrence"": {""type"": """&G3&""", ""day_of_month"": 1}, ""invoice_lines"": [{""label"": """&E3&""", ""quantity"": 1, ""raw_currency_unit_price"": "&SUBSTITUTE(TEXT(H3,"0.00"),",",".")&", ""vat_rate"": """&K3&""""&IF(D3<>"",", ""product_id"": "&D3,"")&"}"&IF(I3>0,", {""label"": ""Provision sur charges"", ""quantity"": 1, ""raw_currency_unit_price"": "&SUBSTITUTE(TEXT(I3,"0.00"),",",".")&", ""vat_rate"": """&K3&"""}","")&"]}"
A4: B03 | B4: =INDEX(Baux!$C:$C,MATCH($A4,Baux!$A:$A,0)) | C4: =IF(INDEX(Baux!$R:$R,MATCH($A4,Baux!$A:$A,0))="","À RENSEIGNER",INDEX(Baux!$R:$R,MATCH($A4,Baux!$A:$A,0))) | D4: =IF(INDEX(Baux!$S:$S,MATCH($A4,Baux!$A:$A,0))="","",INDEX(Baux!$S:$S,MATCH($A4,Baux!$A:$A,0))) | E4: ="Loyer "&INDEX(Baux!$B:$B,MATCH($A4,Baux!$A:$A,0))&" – échéance "&LOWER(F4) | F4: =INDEX(Baux!$L:$L,MATCH($A4,Baux!$A:$A,0)) | G4: =IF(F4="Mensuelle","monthly",IF(F4="Trimestrielle","quarterly",IF(F4="Semestrielle","semiannual","yearly"))) | H4: =ROUND(INDEX(Alertes!$G:$G,MATCH(A4,Alertes!$A:$A,0))/IF(F4="Mensuelle",12,IF(F4="Trimestrielle",4,IF(F4="Semestrielle",2,1))),2) | I4: =ROUND(IF(INDEX(Baux!$J:$J,MATCH($A4,Baux!$A:$A,0))="",0,INDEX(Baux!$J:$J,MATCH($A4,Baux!$A:$A,0)))/IF(F4="Mensuelle",12,IF(F4="Trimestrielle",4,IF(F4="Semestrielle",2,1))),2) | J4: =INDEX(Baux!$K:$K,MATCH($A4,Baux!$A:$A,0)) | K4: =IF(J4=20,"FR_200",IF(J4=10,"FR_100",IF(J4=5.5,"FR_55",IF(J4=2.1,"FR_21","exempt")))) | L4: =DATE(YEAR(TODAY()),MONTH(TODAY())+1,1) | M4: ="{""customer_id"": "&C4&", ""start"": """&YEAR(L4)&"-"&TEXT(MONTH(L4),"00")&"-"&TEXT(DAY(L4),"00")&""", ""currency"": ""EUR"", ""recurrence"": {""type"": """&G4&""", ""day_of_month"": 1}, ""invoice_lines"": [{""label"": """&E4&""", ""quantity"": 1, ""raw_currency_unit_price"": "&SUBSTITUTE(TEXT(H4,"0.00"),",",".")&", ""vat_rate"": """&K4&""""&IF(D4<>"",", ""product_id"": "&D4,"")&"}"&IF(I4>0,", {""label"": ""Provision sur charges"", ""quantity"": 1, ""raw_currency_unit_price"": "&SUBSTITUTE(TEXT(I4,"0.00"),",",".")&", ""vat_rate"": """&K4&"""}","")&"]}"
A5: B04 | B5: =INDEX(Baux!$C:$C,MATCH($A5,Baux!$A:$A,0)) | C5: =IF(INDEX(Baux!$R:$R,MATCH($A5,Baux!$A:$A,0))="","À RENSEIGNER",INDEX(Baux!$R:$R,MATCH($A5,Baux!$A:$A,0))) | D5: =IF(INDEX(Baux!$S:$S,MATCH($A5,Baux!$A:$A,0))="","",INDEX(Baux!$S:$S,MATCH($A5,Baux!$A:$A,0))) | E5: ="Loyer "&INDEX(Baux!$B:$B,MATCH($A5,Baux!$A:$A,0))&" – échéance "&LOWER(F5) | F5: =INDEX(Baux!$L:$L,MATCH($A5,Baux!$A:$A,0)) | G5: =IF(F5="Mensuelle","monthly",IF(F5="Trimestrielle","quarterly",IF(F5="Semestrielle","semiannual","yearly"))) | H5: =ROUND(INDEX(Alertes!$G:$G,MATCH(A5,Alertes!$A:$A,0))/IF(F5="Mensuelle",12,IF(F5="Trimestrielle",4,IF(F5="Semestrielle",2,1))),2) | I5: =ROUND(IF(INDEX(Baux!$J:$J,MATCH($A5,Baux!$A:$A,0))="",0,INDEX(Baux!$J:$J,MATCH($A5,Baux!$A:$A,0)))/IF(F5="Mensuelle",12,IF(F5="Trimestrielle",4,IF(F5="Semestrielle",2,1))),2) | J5: =INDEX(Baux!$K:$K,MATCH($A5,Baux!$A:$A,0)) | K5: =IF(J5=20,"FR_200",IF(J5=10,"FR_100",IF(J5=5.5,"FR_55",IF(J5=2.1,"FR_21","exempt")))) | L5: =DATE(YEAR(TODAY()),MONTH(TODAY())+1,1) | M5: ="{""customer_id"": "&C5&", ""start"": """&YEAR(L5)&"-"&TEXT(MONTH(L5),"00")&"-"&TEXT(DAY(L5),"00")&""", ""currency"": ""EUR"", ""recurrence"": {""type"": """&G5&""", ""day_of_month"": 1}, ""invoice_lines"": [{""label"": """&E5&""", ""quantity"": 1, ""raw_currency_unit_price"": "&SUBSTITUTE(TEXT(H5,"0.00"),",",".")&", ""vat_rate"": """&K5&""""&IF(D5<>"",", ""product_id"": "&D5,"")&"}"&IF(I5>0,", {""label"": ""Provision sur charges"", ""quantity"": 1, ""raw_currency_unit_price"": "&SUBSTITUTE(TEXT(I5,"0.00"),",",".")&", ""vat_rate"": """&K5&"""}","")&"]}"
A7: Schéma indicatif : les noms de champs (recurrence, invoice_lines, raw_currency_unit_price, vat_rate) sont à valider contre https://pennylane.readme.io/reference/postbillingsubscriptions avant tout envoi. Le mapping est modifiable dans config/pennylane_mapping.json.
